{
"meta":{"test_sets":[],"test_metrics":[],"learn_metrics":[{"best_value":"Min","name":"Logloss"}],"launch_mode":"Train","parameters":"","iteration_count":1000,"learn_sets":["learn"],"name":"experiment"},
"iterations":[
{"learn":[0.5919976166],"iteration":0,"passed_time":0.04829663811,"remaining_time":48.24834147},
{"learn":[0.5111564669],"iteration":1,"passed_time":0.06181763596,"remaining_time":30.84700034},
{"learn":[0.4437680327],"iteration":2,"passed_time":0.07806384286,"remaining_time":25.94321711},
{"learn":[0.3949643859],"iteration":3,"passed_time":0.09253665884,"remaining_time":23.04162805},
{"learn":[0.3589332924],"iteration":4,"passed_time":0.1060605298,"remaining_time":21.10604542},
{"learn":[0.3262284044],"iteration":5,"passed_time":0.1197241309,"remaining_time":19.83429769},
{"learn":[0.3025908431],"iteration":6,"passed_time":0.1342289187,"remaining_time":19.04133089},
{"learn":[0.2821430761],"iteration":7,"passed_time":0.1501555629,"remaining_time":18.6192898},
{"learn":[0.2642901094],"iteration":8,"passed_time":0.1645533891,"remaining_time":18.11915651},
{"learn":[0.2503124401],"iteration":9,"passed_time":0.1774472617,"remaining_time":17.56727891},
{"learn":[0.2384133149],"iteration":10,"passed_time":0.1902043735,"remaining_time":17.10110231},
{"learn":[0.2282558626],"iteration":11,"passed_time":0.2026143875,"remaining_time":16.6819179},
{"learn":[0.2214652573],"iteration":12,"passed_time":0.216406048,"remaining_time":16.43021303},
{"learn":[0.2153006981],"iteration":13,"passed_time":0.2292057319,"remaining_time":16.14263226},
{"learn":[0.2105319094],"iteration":14,"passed_time":0.2418401398,"remaining_time":15.88083585},
{"learn":[0.206783341],"iteration":15,"passed_time":0.2545720023,"remaining_time":15.65617814},
{"learn":[0.2019708662],"iteration":16,"passed_time":0.2672008002,"remaining_time":15.45049333},
{"learn":[0.1988239748],"iteration":17,"passed_time":0.278970564,"remaining_time":15.2193941},
{"learn":[0.1958131111],"iteration":18,"passed_time":0.2900415875,"remaining_time":14.97530512},
{"learn":[0.1933945351],"iteration":19,"passed_time":0.3004265788,"remaining_time":14.72090236},
{"learn":[0.1917165662],"iteration":20,"passed_time":0.3111718713,"remaining_time":14.50653628},
{"learn":[0.1896586729],"iteration":21,"passed_time":0.3227810831,"remaining_time":14.34908633},
{"learn":[0.1879643176],"iteration":22,"passed_time":0.3344655697,"remaining_time":14.20751572},
{"learn":[0.1867660704],"iteration":23,"passed_time":0.3464927201,"remaining_time":14.09070395},
{"learn":[0.1858422801],"iteration":24,"passed_time":0.3587392979,"remaining_time":13.99083262},
{"learn":[0.1849941217],"iteration":25,"passed_time":0.3748561883,"remaining_time":14.04268952},
{"learn":[0.1843353653],"iteration":26,"passed_time":0.3871281171,"remaining_time":13.95095029},
{"learn":[0.1834261802],"iteration":27,"passed_time":0.3990805235,"remaining_time":13.85379532},
{"learn":[0.1826286975],"iteration":28,"passed_time":0.411603011,"remaining_time":13.78160427},
{"learn":[0.1820285968],"iteration":29,"passed_time":0.4238681476,"remaining_time":13.7050701},
{"learn":[0.1814118861],"iteration":30,"passed_time":0.4371301094,"remaining_time":13.66384116},
{"learn":[0.1808995176],"iteration":31,"passed_time":0.4501074616,"remaining_time":13.61575071},
{"learn":[0.1805544467],"iteration":32,"passed_time":0.4636006676,"remaining_time":13.58490441},
{"learn":[0.1800846103],"iteration":33,"passed_time":0.4751880002,"remaining_time":13.50092965},
{"learn":[0.1796821445],"iteration":34,"passed_time":0.4877396741,"remaining_time":13.44767959},
{"learn":[0.1793951638],"iteration":35,"passed_time":0.5004080487,"remaining_time":13.39981553},
{"learn":[0.1790918273],"iteration":36,"passed_time":0.5127703893,"remaining_time":13.34588878},
{"learn":[0.1787323943],"iteration":37,"passed_time":0.5242735312,"remaining_time":13.27239834},
{"learn":[0.1783851475],"iteration":38,"passed_time":0.5362450419,"remaining_time":13.21362783},
{"learn":[0.1780866002],"iteration":39,"passed_time":0.5487453196,"remaining_time":13.16988767},
{"learn":[0.177876711],"iteration":40,"passed_time":0.5605315684,"remaining_time":13.1109701},
{"learn":[0.1776066552],"iteration":41,"passed_time":0.5715802965,"remaining_time":13.03747438},
{"learn":[0.1773826218],"iteration":42,"passed_time":0.5839741276,"remaining_time":12.99681954},
{"learn":[0.1772001655],"iteration":43,"passed_time":0.5960442308,"remaining_time":12.95041556},
{"learn":[0.1770564951],"iteration":44,"passed_time":0.6080200692,"remaining_time":12.90353702},
{"learn":[0.1769107603],"iteration":45,"passed_time":0.621374667,"remaining_time":12.88677027},
{"learn":[0.1767670922],"iteration":46,"passed_time":0.6335210609,"remaining_time":12.84565045},
{"learn":[0.1765878321],"iteration":47,"passed_time":0.6462696478,"remaining_time":12.81768135},
{"learn":[0.1764624894],"iteration":48,"passed_time":0.6591228451,"remaining_time":12.79236379},
{"learn":[0.1763329023],"iteration":49,"passed_time":0.6726034264,"remaining_time":12.7794651},
{"learn":[0.1761924774],"iteration":50,"passed_time":0.6860155071,"remaining_time":12.76526895},
{"learn":[0.1761139843],"iteration":51,"passed_time":0.6980186745,"remaining_time":12.72541737},
{"learn":[0.1760249867],"iteration":52,"passed_time":0.7102789323,"remaining_time":12.69121036},
{"learn":[0.1759330301],"iteration":53,"passed_time":0.7220697895,"remaining_time":12.64959298},
{"learn":[0.1758538157],"iteration":54,"passed_time":0.7336551786,"remaining_time":12.60552989},
{"learn":[0.1757812091],"iteration":55,"passed_time":0.7446564717,"remaining_time":12.55278052},
{"learn":[0.1756875921],"iteration":56,"passed_time":0.7559550672,"remaining_time":12.50641453},
{"learn":[0.1756503624],"iteration":57,"passed_time":0.7665705593,"remaining_time":12.45016322},
{"learn":[0.1755443399],"iteration":58,"passed_time":0.7780161781,"remaining_time":12.40869871},
{"learn":[0.1754563152],"iteration":59,"passed_time":0.7890813656,"remaining_time":12.36227473},
{"learn":[0.1753905125],"iteration":60,"passed_time":0.7995821122,"remaining_time":12.30832137},
{"learn":[0.175288929],"iteration":61,"passed_time":0.8106788161,"remaining_time":12.26478596},
{"learn":[0.1752379469],"iteration":62,"passed_time":0.8214449981,"remaining_time":12.2173645},
{"learn":[0.1751850489],"iteration":63,"passed_time":0.8317202107,"remaining_time":12.16390808},
{"learn":[0.1750871981],"iteration":64,"passed_time":0.8427812629,"remaining_time":12.12308432},
{"learn":[0.1750031919],"iteration":65,"passed_time":0.8547794893,"remaining_time":12.09642489},
{"learn":[0.1749368431],"iteration":66,"passed_time":0.8676915849,"remaining_time":12.08292909},
{"learn":[0.174869261],"iteration":67,"passed_time":0.8795861775,"remaining_time":12.05550467},
{"learn":[0.1747762228],"iteration":68,"passed_time":0.8919468652,"remaining_time":12.0348193},
{"learn":[0.1747088033],"iteration":69,"passed_time":0.903710704,"remaining_time":12.00644221},
{"learn":[0.1746203494],"iteration":70,"passed_time":0.9156568091,"remaining_time":11.98091797},
{"learn":[0.1745464119],"iteration":71,"passed_time":0.9268694207,"remaining_time":11.94631698},
{"learn":[0.1745114147],"iteration":72,"passed_time":0.938558235,"remaining_time":11.91840389},
{"learn":[0.1744594364],"iteration":73,"passed_time":0.9502035515,"remaining_time":11.89038498},
{"learn":[0.1744029678],"iteration":74,"passed_time":0.9623304405,"remaining_time":11.8687421},
{"learn":[0.1743352381],"iteration":75,"passed_time":0.9749014449,"remaining_time":11.85274915},
{"learn":[0.1742352115],"iteration":76,"passed_time":0.9874972136,"remaining_time":11.83714192},
{"learn":[0.1741883465],"iteration":77,"passed_time":0.9995460527,"remaining_time":11.81514693},
{"learn":[0.1741355955],"iteration":78,"passed_time":1.011168839,"remaining_time":11.78843672},
{"learn":[0.1740932743],"iteration":79,"passed_time":1.022558021,"remaining_time":11.75941724},
{"learn":[0.1740519404],"iteration":80,"passed_time":1.035178339,"remaining_time":11.74480116},
{"learn":[0.1740137388],"iteration":81,"passed_time":1.047570738,"remaining_time":11.72768217},
{"learn":[0.1739413467],"iteration":82,"passed_time":1.059351447,"remaining_time":11.703919},
{"learn":[0.1738830668],"iteration":83,"passed_time":1.071718041,"remaining_time":11.68683007},
{"learn":[0.1738482091],"iteration":84,"passed_time":1.08419104,"remaining_time":11.67099766},
{"learn":[0.1737798682],"iteration":85,"passed_time":1.096009196,"remaining_time":11.64828378},
{"learn":[0.1737067815],"iteration":86,"passed_time":1.107796559,"remaining_time":11.62549722},
{"learn":[0.1736261863],"iteration":87,"passed_time":1.119710286,"remaining_time":11.60427024},
{"learn":[0.1735842345],"iteration":88,"passed_time":1.131420216,"remaining_time":11.58116648},
{"learn":[0.1735312525],"iteration":89,"passed_time":1.143285447,"remaining_time":11.55988618},
{"learn":[0.1735003714],"iteration":90,"passed_time":1.15597339,"remaining_time":11.5470309},
{"learn":[0.1734713935],"iteration":91,"passed_time":1.181355639,"remaining_time":11.65946653},
{"learn":[0.1734347469],"iteration":92,"passed_time":1.192236877,"remaining_time":11.62751449},
{"learn":[0.1733703573],"iteration":93,"passed_time":1.203257194,"remaining_time":11.59735126},
{"learn":[0.1733249137],"iteration":94,"passed_time":1.215680649,"remaining_time":11.58095776},
{"learn":[0.1732923878],"iteration":95,"passed_time":1.227472003,"remaining_time":11.55869469},
{"learn":[0.1732671349],"iteration":96,"passed_time":1.238506956,"remaining_time":11.52960599},
{"learn":[0.1732067555],"iteration":97,"passed_time":1.249956532,"remaining_time":11.50470196},
{"learn":[0.1731847982],"iteration":98,"passed_time":1.261104618,"remaining_time":11.47732586},
{"learn":[0.1731321526],"iteration":99,"passed_time":1.272119155,"remaining_time":11.44907239},
{"learn":[0.1730757508],"iteration":100,"passed_time":1.282768978,"remaining_time":11.41791397},
{"learn":[0.1730540788],"iteration":101,"passed_time":1.293244279,"remaining_time":11.3856212},
{"learn":[0.1730251995],"iteration":102,"passed_time":1.304017794,"remaining_time":11.35634914},
{"learn":[0.1729689326],"iteration":103,"passed_time":1.314451561,"remaining_time":11.32450576},
{"learn":[0.1729013822],"iteration":104,"passed_time":1.325614213,"remaining_time":11.29928305},
{"learn":[0.1728682191],"iteration":105,"passed_time":1.336382358,"remaining_time":11.27099838},
{"learn":[0.172821527],"iteration":106,"passed_time":1.347320889,"remaining_time":11.24446312},
{"learn":[0.1727911248],"iteration":107,"passed_time":1.35980073,"remaining_time":11.23094677},
{"learn":[0.1727580309],"iteration":108,"passed_time":1.372676495,"remaining_time":11.22068584},
{"learn":[0.1727172765],"iteration":109,"passed_time":1.386777505,"remaining_time":11.22029072},
{"learn":[0.1727019171],"iteration":110,"passed_time":1.398796721,"remaining_time":11.20297554},
{"learn":[0.172690477],"iteration":111,"passed_time":1.410420238,"remaining_time":11.1826176},
{"learn":[0.1726671161],"iteration":112,"passed_time":1.422934902,"remaining_time":11.16940936},
{"learn":[0.1726467226],"iteration":113,"passed_time":1.434607668,"remaining_time":11.14967012},
{"learn":[0.1726197596],"iteration":114,"passed_time":1.44716421,"remaining_time":11.1368724},
{"learn":[0.1725904508],"iteration":115,"passed_time":1.461852863,"remaining_time":11.14032699},
{"learn":[0.17255676],"iteration":116,"passed_time":1.474599051,"remaining_time":11.12881164},
{"learn":[0.1725345161],"iteration":117,"passed_time":1.486429088,"remaining_time":11.11042759},
{"learn":[0.1725078602],"iteration":118,"passed_time":1.498345535,"remaining_time":11.09279341},
{"learn":[0.1724614284],"iteration":119,"passed_time":1.511464651,"remaining_time":11.08407411},
{"learn":[0.172456366],"iteration":120,"passed_time":1.522923561,"remaining_time":11.06322157},
{"learn":[0.1724366065],"iteration":121,"passed_time":1.535711582,"remaining_time":11.05208827},
{"learn":[0.1724209567],"iteration":122,"passed_time":1.548019936,"remaining_time":11.037508},
{"learn":[0.1723766096],"iteration":123,"passed_time":1.560587414,"remaining_time":11.02479496},
{"learn":[0.1723479668],"iteration":124,"passed_time":1.573761248,"remaining_time":11.01632874},
{"learn":[0.1723087202],"iteration":125,"passed_time":1.586222079,"remaining_time":11.00284204},
{"learn":[0.1722688833],"iteration":126,"passed_time":1.598779215,"remaining_time":10.9900335},
{"learn":[0.1722336154],"iteration":127,"passed_time":1.610693824,"remaining_time":10.97285167},
{"learn":[0.172196038],"iteration":128,"passed_time":1.623177071,"remaining_time":10.95959092},
{"learn":[0.1721612176],"iteration":129,"passed_time":1.636558587,"remaining_time":10.95235362},
{"learn":[0.1721298734],"iteration":130,"passed_time":1.649642339,"remaining_time":10.94304727},
{"learn":[0.1720936459],"iteration":131,"passed_time":1.66202164,"remaining_time":10.92905139},
{"learn":[0.1720493264],"iteration":132,"passed_time":1.674847085,"remaining_time":10.91798814},
{"learn":[0.1720204255],"iteration":133,"passed_time":1.687292865,"remaining_time":10.90444493},
{"learn":[0.1719739957],"iteration":134,"passed_time":1.700468368,"remaining_time":10.89559361},
{"learn":[0.1719398475],"iteration":135,"passed_time":1.712703931,"remaining_time":10.88070733},
{"learn":[0.1719034177],"iteration":136,"passed_time":1.725363186,"remaining_time":10.86852868},
{"learn":[0.1718703176],"iteration":137,"passed_time":1.739839801,"remaining_time":10.86769499},
{"learn":[0.1718294761],"iteration":138,"passed_time":1.754024896,"remaining_time":10.86485925},
{"learn":[0.1718118522],"iteration":139,"passed_time":1.767556755,"remaining_time":10.85784864},
{"learn":[0.1717937834],"iteration":140,"passed_time":1.780961278,"remaining_time":10.84996977},
{"learn":[0.171768438],"iteration":141,"passed_time":1.794092861,"remaining_time":10.84036391},
{"learn":[0.171742948],"iteration":142,"passed_time":1.807622119,"remaining_time":10.833092},
{"learn":[0.1717052244],"iteration":143,"passed_time":1.819913471,"remaining_time":10.81837452},
{"learn":[0.17165361],"iteration":144,"passed_time":1.832526845,"remaining_time":10.80558933},
{"learn":[0.1716094433],"iteration":145,"passed_time":1.846467408,"remaining_time":10.80056964},
{"learn":[0.1715912818],"iteration":146,"passed_time":1.857972949,"remaining_time":10.78129881},
{"learn":[0.1715296939],"iteration":147,"passed_time":1.87010905,"remaining_time":10.76576291},
{"learn":[0.1714828426],"iteration":148,"passed_time":1.882120933,"remaining_time":10.74956318},
{"learn":[0.1714735853],"iteration":149,"passed_time":1.894075974,"remaining_time":10.73309719},
{"learn":[0.1714291696],"iteration":150,"passed_time":1.905344756,"remaining_time":10.71283244},
{"learn":[0.1714112],"iteration":151,"passed_time":1.916821581,"remaining_time":10.69384671},
{"learn":[0.1713807843],"iteration":152,"passed_time":1.927969857,"remaining_time":10.67314032},
{"learn":[0.1713252958],"iteration":153,"passed_time":1.938885317,"remaining_time":10.65127908},
{"learn":[0.1713117579],"iteration":154,"passed_time":1.949679078,"remaining_time":10.62889562},
{"learn":[0.1712583946],"iteration":155,"passed_time":1.96177726,"remaining_time":10.61371799},
{"learn":[0.1712342075],"iteration":156,"passed_time":1.973530119,"remaining_time":10.59672542},
{"learn":[0.1712010348],"iteration":157,"passed_time":1.985222205,"remaining_time":10.57947529},
{"learn":[0.1711590838],"iteration":158,"passed_time":1.997282595,"remaining_time":10.56424316},
{"learn":[0.1711149625],"iteration":159,"passed_time":2.009951344,"remaining_time":10.55224456},
{"learn":[0.171060479],"iteration":160,"passed_time":2.022114593,"remaining_time":10.53760337},
{"learn":[0.1710362316],"iteration":161,"passed_time":2.034043792,"remaining_time":10.52178208},
{"learn":[0.1710113086],"iteration":162,"passed_time":2.04622279,"remaining_time":10.50729126},
{"learn":[0.1709672276],"iteration":163,"passed_time":2.058659153,"remaining_time":10.49414056},
{"learn":[0.1709329061],"iteration":164,"passed_time":2.070577519,"remaining_time":10.47837714},
{"learn":[0.1708983584],"iteration":165,"passed_time":2.082720396,"remaining_time":10.46378801},
{"learn":[0.170870147],"iteration":166,"passed_time":2.094633342,"remaining_time":10.44808128},
{"learn":[0.1708456713],"iteration":167,"passed_time":2.107115872,"remaining_time":10.43524051},
{"learn":[0.1708019604],"iteration":168,"passed_time":2.119463422,"remaining_time":10.42174026},
{"learn":[0.1707651257],"iteration":169,"passed_time":2.131747372,"remaining_time":10.40794305},
{"learn":[0.1707544665],"iteration":170,"passed_time":2.14323136,"remaining_time":10.39028536},
{"learn":[0.170727141],"iteration":171,"passed_time":2.155419563,"remaining_time":10.37608952},
{"learn":[0.1706689615],"iteration":172,"passed_time":2.167300852,"remaining_time":10.36044974},
{"learn":[0.1706373016],"iteration":173,"passed_time":2.179876765,"remaining_time":10.34815062},
{"learn":[0.1705800597],"iteration":174,"passed_time":2.192094242,"remaining_time":10.33415857},
{"learn":[0.1705476063],"iteration":175,"passed_time":2.204298945,"remaining_time":10.32012688},
{"learn":[0.1705177944],"iteration":176,"passed_time":2.215457515,"remaining_time":10.30125161},
{"learn":[0.1704872035],"iteration":177,"passed_time":2.227906505,"remaining_time":10.28842218},
{"learn":[0.1704447819],"iteration":178,"passed_time":2.239608002,"remaining_time":10.27216855},
{"learn":[0.1704100659],"iteration":179,"passed_time":2.251482455,"remaining_time":10.25675341},
{"learn":[0.1703974299],"iteration":180,"passed_time":2.2627865,"remaining_time":10.23879637},
{"learn":[0.1703467845],"iteration":181,"passed_time":2.274766115,"remaining_time":10.2239488},
{"learn":[0.1703335707],"iteration":182,"passed_time":2.286829411,"remaining_time":10.20950617},
{"learn":[0.170300071],"iteration":183,"passed_time":2.299149105,"remaining_time":10.19622646},
{"learn":[0.1702554344],"iteration":184,"passed_time":2.312228339,"remaining_time":10.18630322},
{"learn":[0.1702096065],"iteration":185,"passed_time":2.325360519,"remaining_time":10.17657775},
{"learn":[0.170191899],"iteration":186,"passed_time":2.337710137,"remaining_time":10.16341359},
{"learn":[0.170152266],"iteration":187,"passed_time":2.350680877,"remaining_time":10.15294081},
{"learn":[0.1701046934],"iteration":188,"passed_time":2.363264514,"remaining_time":10.14078053},
{"learn":[0.1700556748],"iteration":189,"passed_time":2.375966743,"remaining_time":10.12912138},
{"learn":[0.1700137641],"iteration":190,"passed_time":2.389581878,"remaining_time":10.12131801},
{"learn":[0.1699743102],"iteration":191,"passed_time":2.403070437,"remaining_time":10.11292142},
{"learn":[0.1699186362],"iteration":192,"passed_time":2.414557619,"remaining_time":10.09610362},
{"learn":[0.1698911857],"iteration":193,"passed_time":2.425099138,"remaining_time":10.07541188},
{"learn":[0.1698426363],"iteration":194,"passed_time":2.435751627,"remaining_time":10.05528236},
{"learn":[0.1698397263],"iteration":195,"passed_time":2.446478849,"remaining_time":10.03555609},
{"learn":[0.1698138204],"iteration":196,"passed_time":2.457078242,"remaining_time":10.01540014},
{"learn":[0.1697711646],"iteration":197,"passed_time":2.468283911,"remaining_time":9.997796448},
{"learn":[0.1697259258],"iteration":198,"passed_time":2.479557482,"remaining_time":9.980530367},
{"learn":[0.1696974967],"iteration":199,"passed_time":2.490401714,"remaining_time":9.961606854},
{"learn":[0.1696638838],"iteration":200,"passed_time":2.501316922,"remaining_time":9.943045876},
{"learn":[0.1696497943],"iteration":201,"passed_time":2.51234313,"remaining_time":9.924999098},
{"learn":[0.1696258898],"iteration":202,"passed_time":2.523977497,"remaining_time":9.909409188},
{"learn":[0.1695937266],"iteration":203,"passed_time":2.536364311,"remaining_time":9.896794078},
{"learn":[0.1695632199],"iteration":204,"passed_time":2.549704714,"remaining_time":9.887879256},
{"learn":[0.1695265513],"iteration":205,"passed_time":2.561851739,"remaining_time":9.874321751},
{"learn":[0.1695052171],"iteration":206,"passed_time":2.573023187,"remaining_time":9.857040517},
{"learn":[0.1694804444],"iteration":207,"passed_time":2.58483442,"remaining_time":9.842254139},
{"learn":[0.1694358573],"iteration":208,"passed_time":2.596925856,"remaining_time":9.828556708},
{"learn":[0.1694078269],"iteration":209,"passed_time":2.608897316,"remaining_time":9.814423238},
{"learn":[0.1693974237],"iteration":210,"passed_time":2.619874246,"remaining_time":9.796591374},
{"learn":[0.1693468476],"iteration":211,"passed_time":2.631846718,"remaining_time":9.782524594},
{"learn":[0.1693143861],"iteration":212,"passed_time":2.643898064,"remaining_time":9.768768903},
{"learn":[0.1692683313],"iteration":213,"passed_time":2.655985152,"remaining_time":9.755160416},
{"learn":[0.1692215315],"iteration":214,"passed_time":2.667705377,"remaining_time":9.740226608},
{"learn":[0.1691789774],"iteration":215,"passed_time":2.679387286,"remaining_time":9.725183484},
{"learn":[0.1691510396],"iteration":216,"passed_time":2.691388833,"remaining_time":9.711324683},
{"learn":[0.1691243169],"iteration":217,"passed_time":2.703780406,"remaining_time":9.698882006},
{"learn":[0.1691009456],"iteration":218,"passed_time":2.716520483,"remaining_time":9.687682636},
{"learn":[0.1690676665],"iteration":219,"passed_time":2.728783466,"remaining_time":9.674777742},
{"learn":[0.1690424362],"iteration":220,"passed_time":2.741234525,"remaining_time":9.662541607},
{"learn":[0.1690050309],"iteration":221,"passed_time":2.752291598,"remaining_time":9.645418304},
{"learn":[0.1689914845],"iteration":222,"passed_time":2.764270212,"remaining_time":9.631560334},
{"learn":[0.1689495192],"iteration":223,"passed_time":2.776996348,"remaining_time":9.620308777},
{"learn":[0.1689110831],"iteration":224,"passed_time":2.789281416,"remaining_time":9.607524878},
{"learn":[0.1688884685],"iteration":225,"passed_time":2.801060723,"remaining_time":9.593013271},
{"learn":[0.1688671858],"iteration":226,"passed_time":2.813727078,"remaining_time":9.581546392},
{"learn":[0.1688498674],"iteration":227,"passed_time":2.825430518,"remaining_time":9.566808597},
{"learn":[0.168801804],"iteration":228,"passed_time":2.837426423,"remaining_time":9.553081973},
{"learn":[0.1687714872],"iteration":229,"passed_time":2.849144784,"remaining_time":9.538441234},
{"learn":[0.1687508511],"iteration":230,"passed_time":2.86092035,"remaining_time":9.524016229},
{"learn":[0.1687248856],"iteration":231,"passed_time":2.872788435,"remaining_time":9.509920337},
{"learn":[0.1686860847],"iteration":232,"passed_time":2.884525907,"remaining_time":9.495413607},
{"learn":[0.1686685823],"iteration":233,"passed_time":2.896605024,"remaining_time":9.482048925},
{"learn":[0.1686297324],"iteration":234,"passed_time":2.908913434,"remaining_time":9.469441605},
{"learn":[0.1686068022],"iteration":235,"passed_time":2.92080989,"remaining_time":9.455503204},
{"learn":[0.1685714715],"iteration":236,"passed_time":2.931559052,"remaining_time":9.437888424},
{"learn":[0.1685576934],"iteration":237,"passed_time":2.942837375,"remaining_time":9.422025546},
{"learn":[0.1685294055],"iteration":238,"passed_time":2.954145814,"remaining_time":9.406296923},
{"learn":[0.1684961883],"iteration":239,"passed_time":2.965177732,"remaining_time":9.389729485},
{"learn":[0.1684592308],"iteration":240,"passed_time":2.975512461,"remaining_time":9.371012275},
{"learn":[0.1684278337],"iteration":241,"passed_time":2.986481657,"remaining_time":9.354351636},
{"learn":[0.1683884528],"iteration":242,"passed_time":2.997353678,"remaining_time":9.337435122},
{"learn":[0.1683647096],"iteration":243,"passed_time":3.008286479,"remaining_time":9.320756467},
{"learn":[0.1683597236],"iteration":244,"passed_time":3.019732599,"remaining_time":9.305706579},
{"learn":[0.1683179679],"iteration":245,"passed_time":3.032272662,"remaining_time":9.294038972},
{"learn":[0.1682816649],"iteration":246,"passed_time":3.04474197,"remaining_time":9.282148596},
{"learn":[0.1682442512],"iteration":247,"passed_time":3.056634329,"remaining_time":9.268504093},
{"learn":[0.1682065785],"iteration":248,"passed_time":3.069256895,"remaining_time":9.257076018},
{"learn":[0.1681733615],"iteration":249,"passed_time":3.081505156,"remaining_time":9.244515468},
{"learn":[0.1681486482],"iteration":250,"passed_time":3.09397246,"remaining_time":9.232611047},
{"learn":[0.1681224637],"iteration":251,"passed_time":3.106542543,"remaining_time":9.221007231},
{"learn":[0.1680934814],"iteration":252,"passed_time":3.118542336,"remaining_time":9.207711958},
{"learn":[0.1680527774],"iteration":253,"passed_time":3.130428757,"remaining_time":9.194093909},
{"learn":[0.1680178345],"iteration":254,"passed_time":3.142451169,"remaining_time":9.180886748},
{"learn":[0.1679841837],"iteration":255,"passed_time":3.154773969,"remaining_time":9.168561846},
{"learn":[0.1679529742],"iteration":256,"passed_time":3.166602749,"remaining_time":9.154808727},
{"learn":[0.1679012983],"iteration":257,"passed_time":3.178006493,"remaining_time":9.139848132},
{"learn":[0.1678700677],"iteration":258,"passed_time":3.189820031,"remaining_time":9.126087425},
{"learn":[0.1678591224],"iteration":259,"passed_time":3.202683038,"remaining_time":9.115328648},
{"learn":[0.1678391675],"iteration":260,"passed_time":3.215742317,"remaining_time":9.105109473},
{"learn":[0.1677977064],"iteration":261,"passed_time":3.228349597,"remaining_time":9.093595428},
{"learn":[0.1677657842],"iteration":262,"passed_time":3.240831822,"remaining_time":9.081722634},
{"learn":[0.1677401554],"iteration":263,"passed_time":3.252631359,"remaining_time":9.06794197},
{"learn":[0.1677071544],"iteration":264,"passed_time":3.265084959,"remaining_time":9.055990357},
{"learn":[0.1676669378],"iteration":265,"passed_time":3.277221876,"remaining_time":9.043161115},
{"learn":[0.167647212],"iteration":266,"passed_time":3.288939181,"remaining_time":9.029185092},
{"learn":[0.1676063698],"iteration":267,"passed_time":3.301291688,"remaining_time":9.01696088},
{"learn":[0.1675990237],"iteration":268,"passed_time":3.312804874,"remaining_time":9.00245488},
{"learn":[0.1675658305],"iteration":269,"passed_time":3.325498648,"remaining_time":8.991163012},
{"learn":[0.1675538813],"iteration":270,"passed_time":3.337034833,"remaining_time":8.976746839},
{"learn":[0.1675237186],"iteration":271,"passed_time":3.348811331,"remaining_time":8.962995032},
{"learn":[0.1674839548],"iteration":272,"passed_time":3.361136044,"remaining_time":8.950717597},
{"learn":[0.1674549077],"iteration":273,"passed_time":3.37375279,"remaining_time":8.939213597},
{"learn":[0.1674224376],"iteration":274,"passed_time":3.386088157,"remaining_time":8.926959687},
{"learn":[0.1674114983],"iteration":275,"passed_time":3.398239185,"remaining_time":8.914221629},
{"learn":[0.1673882699],"iteration":276,"passed_time":3.411296811,"remaining_time":8.90385413},
{"learn":[0.1673699571],"iteration":277,"passed_time":3.423816994,"remaining_time":8.892071473},
{"learn":[0.1673305127],"iteration":278,"passed_time":3.434513822,"remaining_time":8.875571561},
{"learn":[0.16729349],"iteration":279,"passed_time":3.44585855,"remaining_time":8.860779128},
{"learn":[0.1672649286],"iteration":280,"passed_time":3.457110141,"remaining_time":8.845772923},
{"learn":[0.1672324059],"iteration":281,"passed_time":3.46796962,"remaining_time":8.82979499},
{"learn":[0.1672000402],"iteration":282,"passed_time":3.479116033,"remaining_time":8.814580197},
{"learn":[0.1671740335],"iteration":283,"passed_time":3.489913171,"remaining_time":8.798513486},
{"learn":[0.1671543444],"iteration":284,"passed_time":3.500278394,"remaining_time":8.781400183},
{"learn":[0.1671117832],"iteration":285,"passed_time":3.511061467,"remaining_time":8.765377228},
{"learn":[0.1670790346],"iteration":286,"passed_time":3.521942494,"remaining_time":8.749634141},
{"learn":[0.1670522285],"iteration":287,"passed_time":3.533339899,"remaining_time":8.735201417},
{"learn":[0.1670008085],"iteration":288,"passed_time":3.545784314,"remaining_time":8.723365562},
{"learn":[0.1669657538],"iteration":289,"passed_time":3.558426078,"remaining_time":8.712008673},
{"learn":[0.1669317292],"iteration":290,"passed_time":3.57130741,"remaining_time":8.701226645},
{"learn":[0.1668932164],"iteration":291,"passed_time":3.583226134,"remaining_time":8.688096242},
{"learn":[0.1668692116],"iteration":292,"passed_time":3.594898978,"remaining_time":8.674380809},
{"learn":[0.166834205],"iteration":293,"passed_time":3.606919977,"remaining_time":8.661515319},
{"learn":[0.1667990465],"iteration":294,"passed_time":3.619466307,"remaining_time":8.649911005},
{"learn":[0.1667422146],"iteration":295,"passed_time":3.631719973,"remaining_time":8.63760426},
{"learn":[0.1667010067],"iteration":296,"passed_time":3.64359431,"remaining_time":8.624399999},
{"learn":[0.1666808082],"iteration":297,"passed_time":3.655251227,"remaining_time":8.610692489},
{"learn":[0.1666499988],"iteration":298,"passed_time":3.667561244,"remaining_time":8.598529874},
{"learn":[0.166621858],"iteration":299,"passed_time":3.68076968,"remaining_time":8.588462587},
{"learn":[0.1665923993],"iteration":300,"passed_time":3.693001106,"remaining_time":8.57610556},
{"learn":[0.1665548967],"iteration":301,"passed_time":3.705307121,"remaining_time":8.563921756},
{"learn":[0.1665370932],"iteration":302,"passed_time":3.717876808,"remaining_time":8.552343681},
{"learn":[0.1665230275],"iteration":303,"passed_time":3.730377276,"remaining_time":8.540600606},
{"learn":[0.1665080926],"iteration":304,"passed_time":3.742077872,"remaining_time":8.527029905},
{"learn":[0.1664764315],"iteration":305,"passed_time":3.753911876,"remaining_time":8.513773994},
{"learn":[0.166448696],"iteration":306,"passed_time":3.765716412,"remaining_time":8.500460826},
{"learn":[0.1663949522],"iteration":307,"passed_time":3.777465049,"remaining_time":8.487031864},
{"learn":[0.1663618698],"iteration":308,"passed_time":3.789874585,"remaining_time":8.475091708},
{"learn":[0.1663281051],"iteration":309,"passed_time":3.802000832,"remaining_time":8.462517982},
{"learn":[0.1662993167],"iteration":310,"passed_time":3.813936749,"remaining_time":8.449525467},
{"learn":[0.1662798822],"iteration":311,"passed_time":3.825772367,"remaining_time":8.436318552},
{"learn":[0.1662598011],"iteration":312,"passed_time":3.837721367,"remaining_time":8.423369262},
{"learn":[0.166234252],"iteration":313,"passed_time":3.849609759,"remaining_time":8.410293932},
{"learn":[0.1662129222],"iteration":314,"passed_time":3.861745604,"remaining_time":8.397764249},
{"learn":[0.1661810218],"iteration":315,"passed_time":3.873821646,"remaining_time":8.385107613},
{"learn":[0.1661305622],"iteration":316,"passed_time":3.885427538,"remaining_time":8.371441666},
{"learn":[0.1660983368],"iteration":317,"passed_time":3.8973216,"remaining_time":8.358406701},
{"learn":[0.1660634581],"iteration":318,"passed_time":3.908984177,"remaining_time":8.344884716},
{"learn":[0.1660237363],"iteration":319,"passed_time":3.920792686,"remaining_time":8.331684457},
{"learn":[0.1659908485],"iteration":320,"passed_time":3.931630075,"remaining_time":8.316438695},
{"learn":[0.1659821005],"iteration":321,"passed_time":3.942410433,"remaining_time":8.301100228},
{"learn":[0.1659496519],"iteration":322,"passed_time":3.952897735,"remaining_time":8.285175748},
{"learn":[0.1659277269],"iteration":323,"passed_time":3.963277194,"remaining_time":8.269059825},
{"learn":[0.1658944164],"iteration":324,"passed_time":3.973632821,"remaining_time":8.252929705},
{"learn":[0.1658625896],"iteration":325,"passed_time":3.984256317,"remaining_time":8.237388828},
{"learn":[0.1658439711],"iteration":326,"passed_time":3.995236252,"remaining_time":8.222611614},
{"learn":[0.1658263306],"iteration":327,"passed_time":4.00582159,"remaining_time":8.207049112},
{"learn":[0.1657923897],"iteration":328,"passed_time":4.016481111,"remaining_time":8.191668163},
{"learn":[0.1657688828],"iteration":329,"passed_time":4.027514716,"remaining_time":8.177075333},
{"learn":[0.1657473967],"iteration":330,"passed_time":4.037849972,"remaining_time":8.161092542},
{"learn":[0.1657170026],"iteration":331,"passed_time":4.050120869,"remaining_time":8.149038376},
{"learn":[0.1657108264],"iteration":332,"passed_time":4.06220401,"remaining_time":8.136606831},
{"learn":[0.1656809819],"iteration":333,"passed_time":4.074451024,"remaining_time":8.124504138},
{"learn":[0.1656788943],"iteration":334,"passed_time":4.086129735,"remaining_time":8.111272459},
{"learn":[0.1656486435],"iteration":335,"passed_time":4.09862529,"remaining_time":8.099664263},
{"learn":[0.1656121529],"iteration":336,"passed_time":4.110742431,"remaining_time":8.087306326},
{"learn":[0.1655871563],"iteration":337,"passed_time":4.122320778,"remaining_time":8.073894541},
{"learn":[0.1655701418],"iteration":338,"passed_time":4.133830075,"remaining_time":8.060358937},
{"learn":[0.1655499397],"iteration":339,"passed_time":4.14581756,"remaining_time":8.047763498},
{"learn":[0.1655327493],"iteration":340,"passed_time":4.157762934,"remaining_time":8.035090244},
{"learn":[0.1655079777],"iteration":341,"passed_time":4.170055852,"remaining_time":8.023089914},
{"learn":[0.1654795106],"iteration":342,"passed_time":4.181969387,"remaining_time":8.010361187},
{"learn":[0.1654516099],"iteration":343,"passed_time":4.19422732,"remaining_time":7.99829396},
{"learn":[0.1654165936],"iteration":344,"passed_time":4.205720114,"remaining_time":7.98477297},
{"learn":[0.1654033723],"iteration":345,"passed_time":4.216750709,"remaining_time":7.970390069},
{"learn":[0.165374812],"iteration":346,"passed_time":4.228139386,"remaining_time":7.956700343},
{"learn":[0.1653523827],"iteration":347,"passed_time":4.239557746,"remaining_time":7.943079455},
{"learn":[0.1653053252],"iteration":348,"passed_time":4.251542461,"remaining_time":7.930527627},
{"learn":[0.165290759],"iteration":349,"passed_time":4.263616419,"remaining_time":7.918144778},
{"learn":[0.1652553787],"iteration":350,"passed_time":4.275655827,"remaining_time":7.905699805},
{"learn":[0.165231106],"iteration":351,"passed_time":4.287590412,"remaining_time":7.893064167},
{"learn":[0.1651914425],"iteration":352,"passed_time":4.299401224,"remaining_time":7.880205644},
{"learn":[0.1651641672],"iteration":353,"passed_time":4.311286144,"remaining_time":7.867488275},
{"learn":[0.1651456004],"iteration":354,"passed_time":4.323126987,"remaining_time":7.854695511},
{"learn":[0.1651068941],"iteration":355,"passed_time":4.335193207,"remaining_time":7.842315801},
{"learn":[0.1650841629],"iteration":356,"passed_time":4.347190123,"remaining_time":7.829813023},
{"learn":[0.1650592334],"iteration":357,"passed_time":4.35895052,"remaining_time":7.816888921},
{"learn":[0.1650475509],"iteration":358,"passed_time":4.370911808,"remaining_time":7.804329997},
{"learn":[0.1650106971],"iteration":359,"passed_time":4.382737091,"remaining_time":7.791532607},
{"learn":[0.1649768659],"iteration":360,"passed_time":4.393822461,"remaining_time":7.777430893},
{"learn":[0.1649473041],"iteration":361,"passed_time":4.40683158,"remaining_time":7.76673632},
{"learn":[0.1649179424],"iteration":362,"passed_time":4.419254098,"remaining_time":7.754999615},
{"learn":[0.164894011],"iteration":363,"passed_time":4.432712051,"remaining_time":7.745068309},
{"learn":[0.1648721554],"iteration":364,"passed_time":4.445425345,"remaining_time":7.733822175},
{"learn":[0.1648555147],"iteration":365,"passed_time":4.458033721,"remaining_time":7.722386282},
{"learn":[0.1648261892],"iteration":366,"passed_time":4.47180772,"remaining_time":7.71295446},
{"learn":[0.164796577],"iteration":367,"passed_time":4.48438725,"remaining_time":7.701447668},
{"learn":[0.1647780522],"iteration":368,"passed_time":4.496924374,"remaining_time":7.689862547},
{"learn":[0.1647584028],"iteration":369,"passed_time":4.508876019,"remaining_time":7.677275383},
{"learn":[0.1647177811],"iteration":370,"passed_time":4.520616896,"remaining_time":7.664334307},
{"learn":[0.1646922753],"iteration":371,"passed_time":4.53124434,"remaining_time":7.649520014},
{"learn":[0.1646860966],"iteration":372,"passed_time":4.54165216,"remaining_time":7.634358993},
{"learn":[0.1646612769],"iteration":373,"passed_time":4.55223295,"remaining_time":7.619512905},
{"learn":[0.1646469125],"iteration":374,"passed_time":4.563136187,"remaining_time":7.605226979},
{"learn":[0.1646142071],"iteration":375,"passed_time":4.573666898,"remaining_time":7.590340809},
{"learn":[0.1646034909],"iteration":376,"passed_time":4.584875782,"remaining_time":7.576598441},
{"learn":[0.16459053],"iteration":377,"passed_time":4.597037584,"remaining_time":7.564437506},
{"learn":[0.1645653393],"iteration":378,"passed_time":4.608787492,"remaining_time":7.551601669},
{"learn":[0.1645527971],"iteration":379,"passed_time":4.620285811,"remaining_time":7.53836106},
{"learn":[0.1645386256],"iteration":380,"passed_time":4.632346151,"remaining_time":7.526042696},
{"learn":[0.1645167184],"iteration":381,"passed_time":4.644689141,"remaining_time":7.514182956},
{"learn":[0.1644757509],"iteration":382,"passed_time":4.657377754,"remaining_time":7.502877478},
{"learn":[0.1644447491],"iteration":383,"passed_time":4.6688118,"remaining_time":7.489552262},
{"learn":[0.1644231682],"iteration":384,"passed_time":4.680850375,"remaining_time":7.477202547},
{"learn":[0.1643982389],"iteration":385,"passed_time":4.692380545,"remaining_time":7.464045738},
{"learn":[0.1643705146],"iteration":386,"passed_time":4.704844714,"remaining_time":7.452376768},
{"learn":[0.1643411339],"iteration":387,"passed_time":4.716381338,"remaining_time":7.439240667},
{"learn":[0.1643178755],"iteration":388,"passed_time":4.728066308,"remaining_time":7.426345794},
{"learn":[0.1642886616],"iteration":389,"passed_time":4.739964434,"remaining_time":7.413790526},
{"learn":[0.1642572627],"iteration":390,"passed_time":4.751606688,"remaining_time":7.400840084},
{"learn":[0.1642322884],"iteration":391,"passed_time":4.763539779,"remaining_time":7.388347413},
{"learn":[0.164194015],"iteration":392,"passed_time":4.776264305,"remaining_time":7.377079982},
{"learn":[0.1641563786],"iteration":393,"passed_time":4.788335915,"remaining_time":7.364800924},
{"learn":[0.1641204399],"iteration":394,"passed_time":4.800128625,"remaining_time":7.352095742},
{"learn":[0.1640758727],"iteration":395,"passed_time":4.812809891,"remaining_time":7.34075044},
{"learn":[0.1640653951],"iteration":396,"passed_time":4.824607316,"remaining_time":7.328055948},
{"learn":[0.1640544906],"iteration":397,"passed_time":4.836886702,"remaining_time":7.316094962},
{"learn":[0.1640334216],"iteration":398,"passed_time":4.849001275,"remaining_time":7.303884126},
{"learn":[0.1640178893],"iteration":399,"passed_time":4.86060661,"remaining_time":7.290909914},
{"learn":[0.1639903731],"iteration":400,"passed_time":4.872357495,"remaining_time":7.278159949},
{"learn":[0.1639590815],"iteration":401,"passed_time":4.886418759,"remaining_time":7.268851785},
{"learn":[0.1639586666],"iteration":402,"passed_time":4.897157897,"remaining_time":7.254598671},
{"learn":[0.1639371008],"iteration":403,"passed_time":4.908947732,"remaining_time":7.241912991},
{"learn":[0.1638984404],"iteration":404,"passed_time":4.920875921,"remaining_time":7.229434994},
{"learn":[0.1638689513],"iteration":405,"passed_time":4.932865063,"remaining_time":7.217048885},
{"learn":[0.163839217],"iteration":406,"passed_time":4.945154082,"remaining_time":7.205101648},
{"learn":[0.1638008125],"iteration":407,"passed_time":4.956978139,"remaining_time":7.192478084},
{"learn":[0.1637710025],"iteration":408,"passed_time":4.968634435,"remaining_time":7.179616017},
{"learn":[0.163759202],"iteration":409,"passed_time":4.980503973,"remaining_time":7.167066693},
{"learn":[0.1637395266],"iteration":410,"passed_time":4.992135685,"remaining_time":7.15417985},
{"learn":[0.1637083582],"iteration":411,"passed_time":5.003544869,"remaining_time":7.140981511},
{"learn":[0.1636699314],"iteration":412,"passed_time":5.014542645,"remaining_time":7.127207101},
{"learn":[0.1636461932],"iteration":413,"passed_time":5.025447746,"remaining_time":7.113314926},
{"learn":[0.1636180722],"iteration":414,"passed_time":5.037017678,"remaining_time":7.100374317},
{"learn":[0.1635780319],"iteration":415,"passed_time":5.049233897,"remaining_time":7.088347586},
{"learn":[0.163560735],"iteration":416,"passed_time":5.060114874,"remaining_time":7.074453169},
{"learn":[0.1635419291],"iteration":417,"passed_time":5.071445727,"remaining_time":7.061199553},
{"learn":[0.1635129502],"iteration":418,"passed_time":5.08295508,"remaining_time":7.048202629},
{"learn":[0.1634769346],"iteration":419,"passed_time":5.093851706,"remaining_time":7.034366642},
{"learn":[0.1634575241],"iteration":420,"passed_time":5.1054624,"remaining_time":7.021526674},
{"learn":[0.1634196032],"iteration":421,"passed_time":5.118347241,"remaining_time":7.01043769},
{"learn":[0.1633964048],"iteration":422,"passed_time":5.130294043,"remaining_time":6.998060669},
{"learn":[0.1633583651],"iteration":423,"passed_time":5.14238623,"remaining_time":6.985883181},
{"learn":[0.1633536427],"iteration":424,"passed_time":5.153571146,"remaining_time":6.972478609},
{"learn":[0.1633235323],"iteration":425,"passed_time":5.165884275,"remaining_time":6.960604633},
{"learn":[0.1633201129],"iteration":426,"passed_time":5.176859641,"remaining_time":6.946933429},
{"learn":[0.1632824903],"iteration":427,"passed_time":5.18869047,"remaining_time":6.934418105},
{"learn":[0.1632549092],"iteration":428,"passed_time":5.200902696,"remaining_time":6.922413612},
{"learn":[0.1632204604],"iteration":429,"passed_time":5.213207812,"remaining_time":6.910531286},
{"learn":[0.1631926865],"iteration":430,"passed_time":5.22560337,"remaining_time":6.898766398},
{"learn":[0.1631650645],"iteration":431,"passed_time":5.237590639,"remaining_time":6.886461766},
{"learn":[0.1631446681],"iteration":432,"passed_time":5.250124877,"remaining_time":6.874874839},
{"learn":[0.1631223427],"iteration":433,"passed_time":5.262324216,"remaining_time":6.862846789},
{"learn":[0.1631023647],"iteration":434,"passed_time":5.273861148,"remaining_time":6.849957584},
{"learn":[0.163079663],"iteration":435,"passed_time":5.285768905,"remaining_time":6.837554272},
{"learn":[0.1630542279],"iteration":436,"passed_time":5.298463681,"remaining_time":6.826167168},
{"learn":[0.1630414718],"iteration":437,"passed_time":5.311092333,"remaining_time":6.814689249},
{"learn":[0.1630225424],"iteration":438,"passed_time":5.322884532,"remaining_time":6.802137181},
{"learn":[0.1629851177],"iteration":439,"passed_time":5.335195018,"remaining_time":6.790248205},
{"learn":[0.1629548179],"iteration":440,"passed_time":5.347809292,"remaining_time":6.77874239},
{"learn":[0.1629359991],"iteration":441,"passed_time":5.359878167,"remaining_time":6.766543026},
{"learn":[0.1629072816],"iteration":442,"passed_time":5.372033563,"remaining_time":6.754453035},
{"learn":[0.1628805942],"iteration":443,"passed_time":5.384082953,"remaining_time":6.742230004},
{"learn":[0.1628463083],"iteration":444,"passed_time":5.396400724,"remaining_time":6.730342476},
{"learn":[0.16281545],"iteration":445,"passed_time":5.408572433,"remaining_time":6.718271587},
{"learn":[0.1627733013],"iteration":446,"passed_time":5.420656926,"remaining_time":6.706092349},
{"learn":[0.1627472392],"iteration":447,"passed_time":5.432561918,"remaining_time":6.693692363},
{"learn":[0.1627187227],"iteration":448,"passed_time":5.444600018,"remaining_time":6.681457928},
{"learn":[0.1626875237],"iteration":449,"passed_time":5.457007629,"remaining_time":6.669675991},
{"learn":[0.1626610821],"iteration":450,"passed_time":5.469157874,"remaining_time":6.657577989},
{"learn":[0.1626266113],"iteration":451,"passed_time":5.48064735,"remaining_time":6.644678645},
{"learn":[0.1625892204],"iteration":452,"passed_time":5.492595937,"remaining_time":6.632339906},
{"learn":[0.1625684321],"iteration":453,"passed_time":5.504142867,"remaining_time":6.619519836},
{"learn":[0.1625367621],"iteration":454,"passed_time":5.515042318,"remaining_time":6.60592981},
{"learn":[0.1625254143],"iteration":455,"passed_time":5.525891258,"remaining_time":6.592291326},
{"learn":[0.1624931222],"iteration":456,"passed_time":5.536996674,"remaining_time":6.57896979},
{"learn":[0.1624727777],"iteration":457,"passed_time":5.547561024,"remaining_time":6.565017631},
{"learn":[0.1624571966],"iteration":458,"passed_time":5.558393369,"remaining_time":6.551396106},
{"learn":[0.1624387805],"iteration":459,"passed_time":5.569276676,"remaining_time":6.537846533},
{"learn":[0.1624111396],"iteration":460,"passed_time":5.580024896,"remaining_time":6.524150584},
{"learn":[0.1623846779],"iteration":461,"passed_time":5.59113265,"remaining_time":6.510886073},
{"learn":[0.1623654256],"iteration":462,"passed_time":5.601580732,"remaining_time":6.496865774},
{"learn":[0.1623377988],"iteration":463,"passed_time":5.613597619,"remaining_time":6.484673111},
{"learn":[0.1623171821],"iteration":464,"passed_time":5.626242681,"remaining_time":6.473203945},
{"learn":[0.162292101],"iteration":465,"passed_time":5.638968645,"remaining_time":6.461822439},
{"learn":[0.1622607342],"iteration":466,"passed_time":5.651454727,"remaining_time":6.450161391},
{"learn":[0.162230537],"iteration":467,"passed_time":5.663653443,"remaining_time":6.438170153},
{"learn":[0.1621955473],"iteration":468,"passed_time":5.675739188,"remaining_time":6.426050126},
{"learn":[0.1621572872],"iteration":469,"passed_time":5.688219164,"remaining_time":6.414374802},
{"learn":[0.1621298501],"iteration":470,"passed_time":5.699703768,"remaining_time":6.401578118},
{"learn":[0.1621068211],"iteration":471,"passed_time":5.711887619,"remaining_time":6.389569201},
{"learn":[0.1620685043],"iteration":472,"passed_time":5.724129795,"remaining_time":6.377624528},
{"learn":[0.1620364582],"iteration":473,"passed_time":5.736202667,"remaining_time":6.365490723},
{"learn":[0.1619994469],"iteration":474,"passed_time":5.747968189,"remaining_time":6.353017472},
{"learn":[0.1619714747],"iteration":475,"passed_time":5.759573363,"remaining_time":6.340370677},
{"learn":[0.1619345904],"iteration":476,"passed_time":5.771390097,"remaining_time":6.327960211},
{"learn":[0.1619074022],"iteration":477,"passed_time":5.783452053,"remaining_time":6.315820025},
{"learn":[0.1618876537],"iteration":478,"passed_time":5.795298698,"remaining_time":6.303445975},
{"learn":[0.1618680013],"iteration":479,"passed_time":5.807059119,"remaining_time":6.290980712},
{"learn":[0.1618368269],"iteration":480,"passed_time":5.818819832,"remaining_time":6.278518696},
{"learn":[0.161810813],"iteration":481,"passed_time":5.830961978,"remaining_time":6.266469512},
{"learn":[0.1617859584],"iteration":482,"passed_time":5.84247922,"remaining_time":6.253751049},
{"learn":[0.1617630685],"iteration":483,"passed_time":5.853924854,"remaining_time":6.240961208},
{"learn":[0.1617321931],"iteration":484,"passed_time":5.866364403,"remaining_time":6.229232305},
{"learn":[0.161699195],"iteration":485,"passed_time":5.877774088,"remaining_time":6.216411278},
{"learn":[0.1616714722],"iteration":486,"passed_time":5.890023651,"remaining_time":6.204480766},
{"learn":[0.1616489891],"iteration":487,"passed_time":5.902704978,"remaining_time":6.193001945},
{"learn":[0.1616357949],"iteration":488,"passed_time":5.914542118,"remaining_time":6.180636038},
{"learn":[0.1616109128],"iteration":489,"passed_time":5.926919857,"remaining_time":6.168834953},
{"learn":[0.1615910817],"iteration":490,"passed_time":5.938679668,"remaining_time":6.156390939},
{"learn":[0.1615717775],"iteration":491,"passed_time":5.950636653,"remaining_time":6.144153292},
{"learn":[0.1615512498],"iteration":492,"passed_time":5.962652854,"remaining_time":6.131977681},
{"learn":[0.1615299425],"iteration":493,"passed_time":5.974486858,"remaining_time":6.119616093},
{"learn":[0.1614994316],"iteration":494,"passed_time":5.986042354,"remaining_time":6.106972502},
{"learn":[0.1614811731],"iteration":495,"passed_time":5.998428196,"remaining_time":6.095177038},
{"learn":[0.1614647623],"iteration":496,"passed_time":6.010734521,"remaining_time":6.08329872},
{"learn":[0.1614495401],"iteration":497,"passed_time":6.022180276,"remaining_time":6.070551202},
{"learn":[0.1614304694],"iteration":498,"passed_time":6.033373903,"remaining_time":6.057555763},
{"learn":[0.1614240175],"iteration":499,"passed_time":6.044449509,"remaining_time":6.044449509},
{"learn":[0.1613942785],"iteration":500,"passed_time":6.055690712,"remaining_time":6.031516298},
{"learn":[0.1613880617],"iteration":501,"passed_time":6.066531969,"remaining_time":6.018193068},
{"learn":[0.1613764711],"iteration":502,"passed_time":6.077032487,"remaining_time":6.004543034},
{"learn":[0.1613657352],"iteration":503,"passed_time":6.087938667,"remaining_time":5.99130472},
{"learn":[0.161340909],"iteration":504,"passed_time":6.09868311,"remaining_time":5.977917108},
{"learn":[0.1613179557],"iteration":505,"passed_time":6.109869227,"remaining_time":5.964971142},
{"learn":[0.1612891316],"iteration":506,"passed_time":6.121162681,"remaining_time":5.952136492},
{"learn":[0.1612675614],"iteration":507,"passed_time":6.13344032,"remaining_time":5.940261097},
{"learn":[0.1612501939],"iteration":508,"passed_time":6.145091421,"remaining_time":5.92777974},
{"learn":[0.1612277476],"iteration":509,"passed_time":6.157391546,"remaining_time":5.915925211},
{"learn":[0.1612146591],"iteration":510,"passed_time":6.168545136,"remaining_time":5.902971764},
{"learn":[0.161197562],"iteration":511,"passed_time":6.181168931,"remaining_time":5.891426637},
{"learn":[0.1611719585],"iteration":512,"passed_time":6.193618417,"remaining_time":5.879711831},
{"learn":[0.1611307954],"iteration":513,"passed_time":6.20598202,"remaining_time":5.867912961},
{"learn":[0.1611174636],"iteration":514,"passed_time":6.218345968,"remaining_time":5.856112222},
{"learn":[0.1611111054],"iteration":515,"passed_time":6.230146638,"remaining_time":5.843780955},
{"learn":[0.1610642081],"iteration":516,"passed_time":6.242544713,"remaining_time":5.832009858},
{"learn":[0.1610284526],"iteration":517,"passed_time":6.254912055,"remaining_time":5.820207742},
{"learn":[0.1610032336],"iteration":518,"passed_time":6.266359555,"remaining_time":5.807550956},
{"learn":[0.1609982822],"iteration":519,"passed_time":6.277573539,"remaining_time":5.794683267},
{"learn":[0.1609791184],"iteration":520,"passed_time":6.289397706,"remaining_time":5.782382919},
{"learn":[0.1609572612],"iteration":521,"passed_time":6.300721266,"remaining_time":5.769625987},
{"learn":[0.1609273823],"iteration":522,"passed_time":6.312390866,"remaining_time":5.75719014},
{"learn":[0.1609152007],"iteration":523,"passed_time":6.324905569,"remaining_time":5.745524907},
{"learn":[0.1608843238],"iteration":524,"passed_time":6.337066251,"remaining_time":5.733536132},
{"learn":[0.160868495],"iteration":525,"passed_time":6.348482265,"remaining_time":5.720875653},
{"learn":[0.1608421833],"iteration":526,"passed_time":6.361105367,"remaining_time":5.709303299},
{"learn":[0.1608253122],"iteration":527,"passed_time":6.372843305,"remaining_time":5.696935682},
{"learn":[0.1608064844],"iteration":528,"passed_time":6.384975784,"remaining_time":5.684921728},
{"learn":[0.1607864074],"iteration":529,"passed_time":6.396855424,"remaining_time":5.672683112},
{"learn":[0.1607638458],"iteration":530,"passed_time":6.40964041,"remaining_time":5.661245484},
{"learn":[0.1607353777],"iteration":531,"passed_time":6.422158327,"remaining_time":5.649567851},
{"learn":[0.1607041014],"iteration":532,"passed_time":6.434024118,"remaining_time":5.637315691},
{"learn":[0.1606901615],"iteration":533,"passed_time":6.445729923,"remaining_time":5.624925363},
{"learn":[0.1606597264],"iteration":534,"passed_time":6.45836931,"remaining_time":5.613349026},
{"learn":[0.1606350015],"iteration":535,"passed_time":6.470487453,"remaining_time":5.601317497},
{"learn":[0.1606021224],"iteration":536,"passed_time":6.48237294,"remaining_time":5.589085049},
{"learn":[0.1605779489],"iteration":537,"passed_time":6.49427723,"remaining_time":5.576870038},
{"learn":[0.1605480815],"iteration":538,"passed_time":6.506425587,"remaining_time":5.564864927},
{"learn":[0.1605091006],"iteration":539,"passed_time":6.518546195,"remaining_time":5.552835648},
{"learn":[0.160474188],"iteration":540,"passed_time":6.530002954,"remaining_time":5.540242802},
{"learn":[0.1604545882],"iteration":541,"passed_time":6.540889351,"remaining_time":5.527172182},
{"learn":[0.1604302401],"iteration":542,"passed_time":6.552505135,"remaining_time":5.514723474},
{"learn":[0.1604043124],"iteration":543,"passed_time":6.563566966,"remaining_time":5.501813486},
{"learn":[0.1603804391],"iteration":544,"passed_time":6.574293848,"remaining_time":5.488630644},
{"learn":[0.1603566125],"iteration":545,"passed_time":6.585535752,"remaining_time":5.475885039},
{"learn":[0.1603421581],"iteration":546,"passed_time":6.596526356,"remaining_time":5.462936817},
{"learn":[0.1603167992],"iteration":547,"passed_time":6.607182881,"remaining_time":5.449720187},
{"learn":[0.1603016018],"iteration":548,"passed_time":6.617888264,"remaining_time":5.436553019},
{"learn":[0.1602937062],"iteration":549,"passed_time":6.629881253,"remaining_time":5.424448298},
{"learn":[0.1602727659],"iteration":550,"passed_time":6.642383214,"remaining_time":5.412758735},
{"learn":[0.1602563231],"iteration":551,"passed_time":6.654761694,"remaining_time":5.400966012},
{"learn":[0.1602328157],"iteration":552,"passed_time":6.666509243,"remaining_time":5.388661179},
{"learn":[0.1602099642],"iteration":553,"passed_time":6.678448927,"remaining_time":5.376513035},
{"learn":[0.1601914952],"iteration":554,"passed_time":6.69020383,"remaining_time":5.364217485},
{"learn":[0.1601599152],"iteration":555,"passed_time":6.702459399,"remaining_time":5.352323693},
{"learn":[0.1601381722],"iteration":556,"passed_time":6.714198914,"remaining_time":5.340018167},
{"learn":[0.1601296046],"iteration":557,"passed_time":6.726212631,"remaining_time":5.327931869},
{"learn":[0.1601134844],"iteration":558,"passed_time":6.738113595,"remaining_time":5.315756879},
{"learn":[0.1600801801],"iteration":559,"passed_time":6.75068491,"remaining_time":5.304109572},
{"learn":[0.1600661513],"iteration":560,"passed_time":6.762586435,"remaining_time":5.29193484},
{"learn":[0.1600350929],"iteration":561,"passed_time":6.775211486,"remaining_time":5.280324966},
{"learn":[0.1600036202],"iteration":562,"passed_time":6.787403827,"remaining_time":5.268375617},
{"learn":[0.1599776055],"iteration":563,"passed_time":6.799908503,"remaining_time":5.256666857},
{"learn":[0.1599419269],"iteration":564,"passed_time":6.811930343,"remaining_time":5.244583539},
{"learn":[0.1599284484],"iteration":565,"passed_time":6.824092706,"remaining_time":5.232608188},
{"learn":[0.1598897084],"iteration":566,"passed_time":6.835632443,"remaining_time":5.220156698},
{"learn":[0.1598746687],"iteration":567,"passed_time":6.848015591,"remaining_time":5.208349886},
{"learn":[0.1598456732],"iteration":568,"passed_time":6.85998586,"remaining_time":5.196228305},
{"learn":[0.1598323726],"iteration":569,"passed_time":6.872040469,"remaining_time":5.18417088},
{"learn":[0.1597989799],"iteration":570,"passed_time":6.884102652,"remaining_time":5.172119156},
{"learn":[0.1597826717],"iteration":571,"passed_time":6.896496594,"remaining_time":5.160315633},
{"learn":[0.1597715834],"iteration":572,"passed_time":6.908797791,"remaining_time":5.148440937},
{"learn":[0.1597506084],"iteration":573,"passed_time":6.92122071,"remaining_time":5.136655091},
{"learn":[0.1597153449],"iteration":574,"passed_time":6.932991221,"remaining_time":5.124384815},
{"learn":[0.1596909196],"iteration":575,"passed_time":6.945801053,"remaining_time":5.11288133},
{"learn":[0.1596563241],"iteration":576,"passed_time":6.958126237,"remaining_time":5.101018021},
{"learn":[0.1596411334],"iteration":577,"passed_time":6.970387647,"remaining_time":5.089106552},
{"learn":[0.159629666],"iteration":578,"passed_time":6.982722212,"remaining_time":5.077247066},
{"learn":[0.1596043751],"iteration":579,"passed_time":6.99516651,"remaining_time":5.065465404},
{"learn":[0.1595793125],"iteration":580,"passed_time":7.007058698,"remaining_time":5.053283295},
{"learn":[0.1595373001],"iteration":581,"passed_time":7.018623591,"remaining_time":5.040867115},
{"learn":[0.1595200686],"iteration":582,"passed_time":7.029433311,"remaining_time":5.027913706},
{"learn":[0.1594883119],"iteration":583,"passed_time":7.04079536,"remaining_time":5.015361078},
{"learn":[0.1594529752],"iteration":584,"passed_time":7.052114184,"remaining_time":5.002781857},
{"learn":[0.1594383634],"iteration":585,"passed_time":7.062458228,"remaining_time":4.98951827},
{"learn":[0.1594249158],"iteration":586,"passed_time":7.073327484,"remaining_time":4.976634158},
{"learn":[0.159414836],"iteration":587,"passed_time":7.08435282,"remaining_time":4.963866262},
{"learn":[0.1593799501],"iteration":588,"passed_time":7.095582623,"remaining_time":4.951246957},
{"learn":[0.1593669833],"iteration":589,"passed_time":7.106024163,"remaining_time":4.938084588},
{"learn":[0.1593289324],"iteration":590,"passed_time":7.117007965,"remaining_time":4.925306697},
{"learn":[0.1593162393],"iteration":591,"passed_time":7.12721762,"remaining_time":4.912001333},
{"learn":[0.1593037529],"iteration":592,"passed_time":7.138593194,"remaining_time":4.899506627},
{"learn":[0.1592908611],"iteration":593,"passed_time":7.150648619,"remaining_time":4.887480369},
{"learn":[0.1592627254],"iteration":594,"passed_time":7.163300424,"remaining_time":4.875859952},
{"learn":[0.1592336767],"iteration":595,"passed_time":7.17660422,"remaining_time":4.864678029},
{"learn":[0.1592116667],"iteration":596,"passed_time":7.188848404,"remaining_time":4.852773713},
{"learn":[0.1591882394],"iteration":597,"passed_time":7.200710384,"remaining_time":4.840611328},
{"learn":[0.15916019],"iteration":598,"passed_time":7.212166922,"remaining_time":4.828178524},
{"learn":[0.1591518559],"iteration":599,"passed_time":7.223953025,"remaining_time":4.815968683},
{"learn":[0.1591443803],"iteration":600,"passed_time":7.236602836,"remaining_time":4.804333663},
{"learn":[0.1591185822],"iteration":601,"passed_time":7.249115991,"remaining_time":4.792604924},
{"learn":[0.1590767657],"iteration":602,"passed_time":7.260646492,"remaining_time":4.780226629},
{"learn":[0.159043871],"iteration":603,"passed_time":7.272996987,"remaining_time":4.768388753},
{"learn":[0.1590269262],"iteration":604,"passed_time":7.285527103,"remaining_time":4.756666456},
{"learn":[0.1590178522],"iteration":605,"passed_time":7.297319388,"remaining_time":4.744461781},
{"learn":[0.1589907026],"iteration":606,"passed_time":7.309103864,"remaining_time":4.732253408},
{"learn":[0.1589783318],"iteration":607,"passed_time":7.320934004,"remaining_time":4.720075871},
{"learn":[0.1589735604],"iteration":608,"passed_time":7.333129413,"remaining_time":4.708133991},
{"learn":[0.1589585109],"iteration":609,"passed_time":7.345199921,"remaining_time":4.696111425},
{"learn":[0.158935301],"iteration":610,"passed_time":7.357102703,"remaining_time":4.683981917},
{"learn":[0.15890475],"iteration":611,"passed_time":7.369178166,"remaining_time":4.671962628},
{"learn":[0.1588867896],"iteration":612,"passed_time":7.38169334,"remaining_time":4.660220755},
{"learn":[0.1588579613],"iteration":613,"passed_time":7.394066099,"remaining_time":4.648386831},
{"learn":[0.1588247603],"iteration":614,"passed_time":7.406241966,"remaining_time":4.636427897},
{"learn":[0.158809635],"iteration":615,"passed_time":7.417734511,"remaining_time":4.624042293},
{"learn":[0.1587941732],"iteration":616,"passed_time":7.429715747,"remaining_time":4.611962935},
{"learn":[0.1587748266],"iteration":617,"passed_time":7.441886354,"remaining_time":4.60000095},
{"learn":[0.1587573977],"iteration":618,"passed_time":7.453344165,"remaining_time":4.587599559},
{"learn":[0.1587326165],"iteration":619,"passed_time":7.465624529,"remaining_time":4.575705356},
{"learn":[0.1587149669],"iteration":620,"passed_time":7.47782526,"remaining_time":4.56376131},
{"learn":[0.1587006978],"iteration":621,"passed_time":7.489298819,"remaining_time":4.551374523},
{"learn":[0.1586838379],"iteration":622,"passed_time":7.500623085,"remaining_time":4.538900326},
{"learn":[0.1586574542],"iteration":623,"passed_time":7.51281753,"remaining_time":4.526954153},
{"learn":[0.1586439466],"iteration":624,"passed_time":7.524446608,"remaining_time":4.514667965},
{"learn":[0.1586408834],"iteration":625,"passed_time":7.536055329,"remaining_time":4.502371714},
{"learn":[0.1586208774],"iteration":626,"passed_time":7.547546208,"remaining_time":4.490007553},
{"learn":[0.1585873657],"iteration":627,"passed_time":7.558791453,"remaining_time":4.47750067},
{"learn":[0.1585753541],"iteration":628,"passed_time":7.569610004,"remaining_time":4.464746123},
{"learn":[0.1585707537],"iteration":629,"passed_time":7.581022033,"remaining_time":4.452346273},
{"learn":[0.1585597501],"iteration":630,"passed_time":7.591754885,"remaining_time":4.439552381},
{"learn":[0.1585435063],"iteration":631,"passed_time":7.602190305,"remaining_time":4.426591823},
{"learn":[0.1585245644],"iteration":632,"passed_time":7.612792633,"remaining_time":4.413736013},
{"learn":[0.1584929712],"iteration":633,"passed_time":7.624162932,"remaining_time":4.401330651},
{"learn":[0.1584810445],"iteration":634,"passed_time":7.63472832,"remaining_time":4.388465884},
{"learn":[0.1584446363],"iteration":635,"passed_time":7.646396968,"remaining_time":4.376239774},
{"learn":[0.1584239233],"iteration":636,"passed_time":7.659079085,"remaining_time":4.364592948},
{"learn":[0.1584198672],"iteration":637,"passed_time":7.67141263,"remaining_time":4.352745097},
{"learn":[0.1583932937],"iteration":638,"passed_time":7.684676209,"remaining_time":4.341421145},
{"learn":[0.1583735988],"iteration":639,"passed_time":7.696760167,"remaining_time":4.329427594},
{"learn":[0.158341254],"iteration":640,"passed_time":7.708496761,"remaining_time":4.317239216},
{"learn":[0.1583238002],"iteration":641,"passed_time":7.72077653,"remaining_time":4.305355137},
{"learn":[0.1582937486],"iteration":642,"passed_time":7.732856865,"remaining_time":4.293359099},
{"learn":[0.1582688181],"iteration":643,"passed_time":7.745218825,"remaining_time":4.281518481},
{"learn":[0.1582415065],"iteration":644,"passed_time":7.757898033,"remaining_time":4.269850856},
{"learn":[0.1582210364],"iteration":645,"passed_time":7.769592272,"remaining_time":4.257640347},
{"learn":[0.158206046],"iteration":646,"passed_time":7.781874825,"remaining_time":4.245752416},
{"learn":[0.1581780681],"iteration":647,"passed_time":7.793972602,"remaining_time":4.233762895},
{"learn":[0.1581498691],"iteration":648,"passed_time":7.80609343,"remaining_time":4.221785507},
{"learn":[0.1581369223],"iteration":649,"passed_time":7.818804866,"remaining_time":4.210125697},
{"learn":[0.1581016712],"iteration":650,"passed_time":7.82997957,"remaining_time":4.197638817},
{"learn":[0.1580710587],"iteration":651,"passed_time":7.841899222,"remaining_time":4.185553573},
{"learn":[0.158060816],"iteration":652,"passed_time":7.853442792,"remaining_time":4.173268987},
{"learn":[0.1580523796],"iteration":653,"passed_time":7.865455096,"remaining_time":4.161234653},
{"learn":[0.1580300652],"iteration":654,"passed_time":7.877446756,"remaining_time":4.149189513},
{"learn":[0.1580158234],"iteration":655,"passed_time":7.889644047,"remaining_time":4.137252366},
{"learn":[0.1580077565],"iteration":656,"passed_time":7.901390379,"remaining_time":4.125078996},
{"learn":[0.1579831207],"iteration":657,"passed_time":7.91418523,"remaining_time":4.113451898},
{"learn":[0.1579678481],"iteration":658,"passed_time":7.927077049,"remaining_time":4.101871432},
{"learn":[0.1579447737],"iteration":659,"passed_time":7.93924428,"remaining_time":4.08991372},
{"learn":[0.1579223448],"iteration":660,"passed_time":7.951233823,"remaining_time":4.077864245},
{"learn":[0.1579158925],"iteration":661,"passed_time":7.962865996,"remaining_time":4.065632487},
{"learn":[0.1578877234],"iteration":662,"passed_time":7.974573274,"remaining_time":4.053440714},
{"learn":[0.1578744444],"iteration":663,"passed_time":7.986416985,"remaining_time":4.041319438},
{"learn":[0.1578350637],"iteration":664,"passed_time":7.998607699,"remaining_time":4.029373803},
{"learn":[0.157798066],"iteration":665,"passed_time":8.01088124,"remaining_time":4.01746897},
{"learn":[0.1577761036],"iteration":666,"passed_time":8.022520696,"remaining_time":4.005246465},
{"learn":[0.1577527295],"iteration":667,"passed_time":8.034213638,"remaining_time":3.993052287},
{"learn":[0.1577434127],"iteration":668,"passed_time":8.046053453,"remaining_time":3.980932276},
{"learn":[0.1577133676],"iteration":669,"passed_time":8.057031354,"remaining_time":3.968388577},
{"learn":[0.1576966306],"iteration":670,"passed_time":8.068306858,"remaining_time":3.955995464},
{"learn":[0.1576768145],"iteration":671,"passed_time":8.079467937,"remaining_time":3.943549827},
{"learn":[0.157646428],"iteration":672,"passed_time":8.09090446,"remaining_time":3.93124184},
{"learn":[0.1576176558],"iteration":673,"passed_time":8.102587734,"remaining_time":3.919055788},
{"learn":[0.1576103673],"iteration":674,"passed_time":8.113693635,"remaining_time":3.906593232},
{"learn":[0.1575887176],"iteration":675,"passed_time":8.124694207,"remaining_time":3.894084206},
{"learn":[0.15757119],"iteration":676,"passed_time":8.135417131,"remaining_time":3.881447169},
{"learn":[0.1575450522],"iteration":677,"passed_time":8.146012728,"remaining_time":3.868755307},
{"learn":[0.1575174703],"iteration":678,"passed_time":8.157355396,"remaining_time":3.856422802},
{"learn":[0.1574830824],"iteration":679,"passed_time":8.169570429,"remaining_time":3.844503731},
{"learn":[0.1574620833],"iteration":680,"passed_time":8.181841496,"remaining_time":3.83261004},
{"learn":[0.157440845],"iteration":681,"passed_time":8.194134783,"remaining_time":3.820725603},
{"learn":[0.1574269515],"iteration":682,"passed_time":8.206767758,"remaining_time":3.808997627},
{"learn":[0.1573983012],"iteration":683,"passed_time":8.218432009,"remaining_time":3.796819466},
{"learn":[0.1573679797],"iteration":684,"passed_time":8.230725376,"remaining_time":3.784932107},
{"learn":[0.157342846],"iteration":685,"passed_time":8.242820147,"remaining_time":3.772952662},
{"learn":[0.1573160894],"iteration":686,"passed_time":8.255469592,"remaining_time":3.761225593},
{"learn":[0.1572730664],"iteration":687,"passed_time":8.267071511,"remaining_time":3.749020801},
{"learn":[0.1572585091],"iteration":688,"passed_time":8.278814392,"remaining_time":3.736881387},
{"learn":[0.1572352281],"iteration":689,"passed_time":8.290774236,"remaining_time":3.724840599},
{"learn":[0.1572071019],"iteration":690,"passed_time":8.303079891,"remaining_time":3.712954684},
{"learn":[0.1571848307],"iteration":691,"passed_time":8.315596007,"remaining_time":3.701161229},
{"learn":[0.157172457],"iteration":692,"passed_time":8.328194741,"remaining_time":3.689402288},
{"learn":[0.1571503524],"iteration":693,"passed_time":8.33951182,"remaining_time":3.677075817},
{"learn":[0.1571266991],"iteration":694,"passed_time":8.351312076,"remaining_time":3.664964292},
{"learn":[0.1571036482],"iteration":695,"passed_time":8.3632256,"remaining_time":3.652903136},
{"learn":[0.1570815346],"iteration":696,"passed_time":8.375656614,"remaining_time":3.641067366},
{"learn":[0.1570648654],"iteration":697,"passed_time":8.387654041,"remaining_time":3.629042293},
{"learn":[0.157026221],"iteration":698,"passed_time":8.399571728,"remaining_time":3.616982961},
{"learn":[0.157007249],"iteration":699,"passed_time":8.411155512,"remaining_time":3.604780934},
{"learn":[0.1569965938],"iteration":700,"passed_time":8.422620796,"remaining_time":3.592530125},
{"learn":[0.1569761997],"iteration":701,"passed_time":8.434877227,"remaining_time":3.580617398},
{"learn":[0.1569713458],"iteration":702,"passed_time":8.446648559,"remaining_time":3.568498751},
{"learn":[0.156944249],"iteration":703,"passed_time":8.45856998,"remaining_time":3.556444196},
{"learn":[0.1569217476],"iteration":704,"passed_time":8.470559697,"remaining_time":3.544418597},
{"learn":[0.156902509],"iteration":705,"passed_time":8.482987271,"remaining_time":3.532575436},
{"learn":[0.1568951187],"iteration":706,"passed_time":8.494988915,"remaining_time":3.520554105},
{"learn":[0.1568761601],"iteration":707,"passed_time":8.506997663,"remaining_time":3.508535759},
{"learn":[0.1568492522],"iteration":708,"passed_time":8.518959306,"remaining_time":3.496498107},
{"learn":[0.1568273493],"iteration":709,"passed_time":8.530649062,"remaining_time":3.484349617},
{"learn":[0.1568119356],"iteration":710,"passed_time":8.542392917,"remaining_time":3.472224406},
{"learn":[0.1568070739],"iteration":711,"passed_time":8.554128633,"remaining_time":3.460096975},
{"learn":[0.1567798687],"iteration":712,"passed_time":8.565379994,"remaining_time":3.447775678},
{"learn":[0.1567555811],"iteration":713,"passed_time":8.576503446,"remaining_time":3.435406142},
{"learn":[0.1567424852],"iteration":714,"passed_time":8.587128095,"remaining_time":3.422841269},
{"learn":[0.1567233305],"iteration":715,"passed_time":8.598303319,"remaining_time":3.410500199},
{"learn":[0.1567048406],"iteration":716,"passed_time":8.608961207,"remaining_time":3.397958189},
{"learn":[0.1566876074],"iteration":717,"passed_time":8.620508202,"remaining_time":3.385770631},
{"learn":[0.1566684211],"iteration":718,"passed_time":8.631797917,"remaining_time":3.373484304},
{"learn":[0.1566634892],"iteration":719,"passed_time":8.642195779,"remaining_time":3.360853914},
{"learn":[0.1566473972],"iteration":720,"passed_time":8.652897927,"remaining_time":3.348347464},
{"learn":[0.1566347353],"iteration":721,"passed_time":8.664293235,"remaining_time":3.336112908},
{"learn":[0.1566000982],"iteration":722,"passed_time":8.676523389,"remaining_time":3.324200524},
{"learn":[0.1565849014],"iteration":723,"passed_time":8.688722588,"remaining_time":3.312275462},
{"learn":[0.1565710781],"iteration":724,"passed_time":8.701037363,"remaining_time":3.300393483},
{"learn":[0.1565562208],"iteration":725,"passed_time":8.712803075,"remaining_time":3.288303089},
{"learn":[0.156533022],"iteration":726,"passed_time":8.724901387,"remaining_time":3.276338485},
{"learn":[0.1565045158],"iteration":727,"passed_time":8.73740479,"remaining_time":3.264524867},
{"learn":[0.1564978034],"iteration":728,"passed_time":8.749318588,"remaining_time":3.252490175},
{"learn":[0.1564760973],"iteration":729,"passed_time":8.761205914,"remaining_time":3.240446023},
{"learn":[0.1564594716],"iteration":730,"passed_time":8.772137233,"remaining_time":3.2280505},
{"learn":[0.1564293599],"iteration":731,"passed_time":8.784525949,"remaining_time":3.216192561},
{"learn":[0.1564155061],"iteration":732,"passed_time":8.796372291,"remaining_time":3.204135609},
{"learn":[0.1563875807],"iteration":733,"passed_time":8.808180965,"remaining_time":3.192065581},
{"learn":[0.1563695758],"iteration":734,"passed_time":8.819873536,"remaining_time":3.179954404},
{"learn":[0.1563500672],"iteration":735,"passed_time":8.831613845,"remaining_time":3.167861488},
{"learn":[0.1563246001],"iteration":736,"passed_time":8.843970337,"remaining_time":3.155989415},
{"learn":[0.1563101536],"iteration":737,"passed_time":8.856311947,"remaining_time":3.144110745},
{"learn":[0.1562829575],"iteration":738,"passed_time":8.868188147,"remaining_time":3.13206645},
{"learn":[0.156257738],"iteration":739,"passed_time":8.880120141,"remaining_time":3.120042212},
{"learn":[0.1562313065],"iteration":740,"passed_time":8.892262693,"remaining_time":3.108091819},
{"learn":[0.1562173847],"iteration":741,"passed_time":8.904573574,"remaining_time":3.096199437},
{"learn":[0.1561951484],"iteration":742,"passed_time":8.916984229,"remaining_time":3.08434044},
{"learn":[0.156171854],"iteration":743,"passed_time":8.92969294,"remaining_time":3.072582517},
{"learn":[0.1561550664],"iteration":744,"passed_time":8.942302616,"remaining_time":3.060788144},
{"learn":[0.1561299801],"iteration":745,"passed_time":8.955268585,"remaining_time":3.049112896},
{"learn":[0.1561202881],"iteration":746,"passed_time":8.96700199,"remaining_time":3.037016738},
{"learn":[0.1560957583],"iteration":747,"passed_time":8.979204448,"remaining_time":3.025079573},
{"learn":[0.1560849994],"iteration":748,"passed_time":8.991466996,"remaining_time":3.013161837},
{"learn":[0.1560702575],"iteration":749,"passed_time":9.003997848,"remaining_time":3.001332616},
{"learn":[0.1560532654],"iteration":750,"passed_time":9.016352225,"remaining_time":2.989443015},
{"learn":[0.1560310364],"iteration":751,"passed_time":9.028451224,"remaining_time":2.977467957},
{"learn":[0.1560127539],"iteration":752,"passed_time":9.040809551,"remaining_time":2.965577635},
{"learn":[0.1559770613],"iteration":753,"passed_time":9.052937563,"remaining_time":2.953610929},
{"learn":[0.1559496326],"iteration":754,"passed_time":9.063783954,"remaining_time":2.941227906},
{"learn":[0.1559158563],"iteration":755,"passed_time":9.075181507,"remaining_time":2.929026835},
{"learn":[0.1558910063],"iteration":756,"passed_time":9.086584629,"remaining_time":2.916829676},
{"learn":[0.155867874],"iteration":757,"passed_time":9.098095194,"remaining_time":2.904668914},
{"learn":[0.1558482579],"iteration":758,"passed_time":9.109190947,"remaining_time":2.892378153},
{"learn":[0.1558344746],"iteration":759,"passed_time":9.120226181,"remaining_time":2.880071425},
{"learn":[0.15581468],"iteration":760,"passed_time":9.130785863,"remaining_time":2.867618687},
{"learn":[0.1557891238],"iteration":761,"passed_time":9.142065915,"remaining_time":2.855395916},
{"learn":[0.1557669925],"iteration":762,"passed_time":9.152901742,"remaining_time":2.843037631},
{"learn":[0.1557387185],"iteration":763,"passed_time":9.164501887,"remaining_time":2.830919431},
{"learn":[0.155712587],"iteration":764,"passed_time":9.176710557,"remaining_time":2.818989517},
{"learn":[0.1556906284],"iteration":765,"passed_time":9.189134002,"remaining_time":2.807124486},
{"learn":[0.1556571128],"iteration":766,"passed_time":9.201629261,"remaining_time":2.795279815},
{"learn":[0.1556293757],"iteration":767,"passed_time":9.213742246,"remaining_time":2.78331797},
{"learn":[0.1555990296],"iteration":768,"passed_time":9.22604391,"remaining_time":2.77141241},
{"learn":[0.155572918],"iteration":769,"passed_time":9.238276728,"remaining_time":2.759485256},
{"learn":[0.1555671527],"iteration":770,"passed_time":9.250411239,"remaining_time":2.747528111},
{"learn":[0.1555379119],"iteration":771,"passed_time":9.262145294,"remaining_time":2.735452237},
{"learn":[0.1555119095],"iteration":772,"passed_time":9.274592627,"remaining_time":2.723586709},
{"learn":[0.1555061667],"iteration":773,"passed_time":9.287160135,"remaining_time":2.711754768},
{"learn":[0.15548447],"iteration":774,"passed_time":9.299359183,"remaining_time":2.699813956},
{"learn":[0.155472097],"iteration":775,"passed_time":9.31060246,"remaining_time":2.687596586},
{"learn":[0.155451773],"iteration":776,"passed_time":9.322649047,"remaining_time":2.675612275},
{"learn":[0.1554269629],"iteration":777,"passed_time":9.334953296,"remaining_time":2.663701326},
{"learn":[0.1553992516],"iteration":778,"passed_time":9.347111206,"remaining_time":2.651747852},
{"learn":[0.1553904267],"iteration":779,"passed_time":9.358950081,"remaining_time":2.639703869},
{"learn":[0.1553727995],"iteration":780,"passed_time":9.370776572,"remaining_time":2.627656939},
{"learn":[0.1553431262],"iteration":781,"passed_time":9.38325986,"remaining_time":2.615793669},
{"learn":[0.155332429],"iteration":782,"passed_time":9.394703906,"remaining_time":2.603640801},
{"learn":[0.1553091317],"iteration":783,"passed_time":9.406877282,"remaining_time":2.59169068},
{"learn":[0.1552814421],"iteration":784,"passed_time":9.419007695,"remaining_time":2.579728222},
{"learn":[0.1552615715],"iteration":785,"passed_time":9.431035234,"remaining_time":2.567737328},
{"learn":[0.1552380655],"iteration":786,"passed_time":9.443044833,"remaining_time":2.555741486},
{"learn":[0.1552252286],"iteration":787,"passed_time":9.455319695,"remaining_time":2.543816974},
{"learn":[0.1552182464],"iteration":788,"passed_time":9.466947139,"remaining_time":2.531718437},
{"learn":[0.1552128776],"iteration":789,"passed_time":9.478711842,"remaining_time":2.519657578},
{"learn":[0.1551914943],"iteration":790,"passed_time":9.490469187,"remaining_time":2.507595525},
{"learn":[0.1551649932],"iteration":791,"passed_time":9.502493141,"remaining_time":2.495604259},
{"learn":[0.1551360975],"iteration":792,"passed_time":9.514998939,"remaining_time":2.483738689},
{"learn":[0.155113295],"iteration":793,"passed_time":9.526928555,"remaining_time":2.471722018},
{"learn":[0.1550887927],"iteration":794,"passed_time":9.538913834,"remaining_time":2.45971992},
{"learn":[0.1550718736],"iteration":795,"passed_time":9.550585436,"remaining_time":2.447637473},
{"learn":[0.1550541311],"iteration":796,"passed_time":9.561755308,"remaining_time":2.435428266},
{"learn":[0.155029547],"iteration":797,"passed_time":9.572531288,"remaining_time":2.423121955},
{"learn":[0.1550052706],"iteration":798,"passed_time":9.583295877,"remaining_time":2.41081661},
{"learn":[0.1549900859],"iteration":799,"passed_time":9.594379397,"remaining_time":2.398594849},
{"learn":[0.1549719479],"iteration":800,"passed_time":9.604957062,"remaining_time":2.386250256},
{"learn":[0.1549605752],"iteration":801,"passed_time":9.615534586,"remaining_time":2.373910035},
{"learn":[0.1549396945],"iteration":802,"passed_time":9.626749834,"remaining_time":2.361730657},
{"learn":[0.1549210213],"iteration":803,"passed_time":9.63717888,"remaining_time":2.349362016},
{"learn":[0.1548891876],"iteration":804,"passed_time":9.649971832,"remaining_time":2.337570816},
{"learn":[0.154873938],"iteration":805,"passed_time":9.661094953,"remaining_time":2.325375212},
{"learn":[0.1548467834],"iteration":806,"passed_time":9.673607243,"remaining_time":2.313514495},
{"learn":[0.1548159063],"iteration":807,"passed_time":9.685464849,"remaining_time":2.301496598},
{"learn":[0.1547947705],"iteration":808,"passed_time":9.69820677,"remaining_time":2.289687878},
{"learn":[0.154754615],"iteration":809,"passed_time":9.710304266,"remaining_time":2.277725692},
{"learn":[0.1547345543],"iteration":810,"passed_time":9.722075588,"remaining_time":2.265687159},
{"learn":[0.1547137956],"iteration":811,"passed_time":9.734343754,"remaining_time":2.253764318},
{"learn":[0.1546992496],"iteration":812,"passed_time":9.746721488,"remaining_time":2.241865828},
{"learn":[0.1546833212],"iteration":813,"passed_time":9.758503229,"remaining_time":2.229829976},
{"learn":[0.1546575049],"iteration":814,"passed_time":9.770428562,"remaining_time":2.217827342},
{"learn":[0.1546404037],"iteration":815,"passed_time":9.782641871,"remaining_time":2.205889834},
{"learn":[0.1546170486],"iteration":816,"passed_time":9.794892201,"remaining_time":2.193959942},
{"learn":[0.1546047661],"iteration":817,"passed_time":9.806253313,"remaining_time":2.181831422},
{"learn":[0.1545767682],"iteration":818,"passed_time":9.817810898,"remaining_time":2.169748196},
{"learn":[0.1545632092],"iteration":819,"passed_time":9.829522423,"remaining_time":2.157700044},
{"learn":[0.1545557973],"iteration":820,"passed_time":9.84168759,"remaining_time":2.145751618},
{"learn":[0.1545394683],"iteration":821,"passed_time":9.853413211,"remaining_time":2.133707484},
{"learn":[0.1545252567],"iteration":822,"passed_time":9.865800336,"remaining_time":2.121806391},
{"learn":[0.1545159333],"iteration":823,"passed_time":9.877828889,"remaining_time":2.10982753},
{"learn":[0.1544772139],"iteration":824,"passed_time":9.889778093,"remaining_time":2.097831717},
{"learn":[0.1544600688],"iteration":825,"passed_time":9.901603068,"remaining_time":2.085809847},
{"learn":[0.1544376664],"iteration":826,"passed_time":9.913080137,"remaining_time":2.073715676},
{"learn":[0.1544195986],"iteration":827,"passed_time":9.925709582,"remaining_time":2.061862377},
{"learn":[0.1543937445],"iteration":828,"passed_time":9.938957899,"remaining_time":2.050134862},
{"learn":[0.1543648703],"iteration":829,"passed_time":9.951924272,"remaining_time":2.038345935},
{"learn":[0.154346411],"iteration":830,"passed_time":9.964907849,"remaining_time":2.026557673},
{"learn":[0.1543295134],"iteration":831,"passed_time":9.977223151,"remaining_time":2.014631598},
{"learn":[0.1543129704],"iteration":832,"passed_time":9.99048326,"remaining_time":2.002894003},
{"learn":[0.1543018677],"iteration":833,"passed_time":10.0032617,"remaining_time":1.991056884},
{"learn":[0.1542910745],"iteration":834,"passed_time":10.01559381,"remaining_time":1.979129316},
{"learn":[0.154261156],"iteration":835,"passed_time":10.02942397,"remaining_time":1.967494655},
{"learn":[0.154232482],"iteration":836,"passed_time":10.04200639,"remaining_time":1.955611757},
{"learn":[0.1542023114],"iteration":837,"passed_time":10.05491115,"remaining_time":1.943789506},
{"learn":[0.1541831656],"iteration":838,"passed_time":10.06734065,"remaining_time":1.931873474},
{"learn":[0.1541629707],"iteration":839,"passed_time":10.07898904,"remaining_time":1.919807436},
{"learn":[0.1541440921],"iteration":840,"passed_time":10.08975259,"remaining_time":1.907575103},
{"learn":[0.1541412733],"iteration":841,"passed_time":10.10048732,"remaining_time":1.895340852},
{"learn":[0.15412966],"iteration":842,"passed_time":10.11159386,"remaining_time":1.883179402},
{"learn":[0.1541175888],"iteration":843,"passed_time":10.12231888,"remaining_time":1.870949936},
{"learn":[0.1541009394],"iteration":844,"passed_time":10.13316176,"remaining_time":1.858745649},
{"learn":[0.1540797745],"iteration":845,"passed_time":10.14415898,"remaining_time":1.846572676},
{"learn":[0.1540567895],"iteration":846,"passed_time":10.15509955,"remaining_time":1.834392245},
{"learn":[0.1540314463],"iteration":847,"passed_time":10.16633319,"remaining_time":1.822267269},
{"learn":[0.1540037513],"iteration":848,"passed_time":10.17846937,"remaining_time":1.810304918},
{"learn":[0.1539833858],"iteration":849,"passed_time":10.191412,"remaining_time":1.79848447},
{"learn":[0.1539568043],"iteration":850,"passed_time":10.20333801,"remaining_time":1.786483388},
{"learn":[0.1539387812],"iteration":851,"passed_time":10.21557966,"remaining_time":1.774537311},
{"learn":[0.1539102667],"iteration":852,"passed_time":10.22756837,"remaining_time":1.762546953},
{"learn":[0.1538943041],"iteration":853,"passed_time":10.23911732,"remaining_time":1.750481415},
{"learn":[0.1538820491],"iteration":854,"passed_time":10.25161152,"remaining_time":1.738577393},
{"learn":[0.1538659085],"iteration":855,"passed_time":10.26385328,"remaining_time":1.726629524},
{"learn":[0.153834184],"iteration":856,"passed_time":10.27607297,"remaining_time":1.714677286},
{"learn":[0.1538121585],"iteration":857,"passed_time":10.28861196,"remaining_time":1.702777271},
{"learn":[0.153787496],"iteration":858,"passed_time":10.30110217,"remaining_time":1.690867761},
{"learn":[0.1537635879],"iteration":859,"passed_time":10.31369711,"remaining_time":1.678973948},
{"learn":[0.1537461355],"iteration":860,"passed_time":10.325937,"remaining_time":1.667021189},
{"learn":[0.153716615],"iteration":861,"passed_time":10.33843088,"remaining_time":1.655108424},
{"learn":[0.1536893699],"iteration":862,"passed_time":10.34989915,"remaining_time":1.643031499},
{"learn":[0.1536656661],"iteration":863,"passed_time":10.36168913,"remaining_time":1.631006623},
{"learn":[0.1536376137],"iteration":864,"passed_time":10.37376911,"remaining_time":1.619027549},
{"learn":[0.1536243833],"iteration":865,"passed_time":10.38543175,"remaining_time":1.606983665},
{"learn":[0.1536086845],"iteration":866,"passed_time":10.39741177,"remaining_time":1.594989349},
{"learn":[0.1535807873],"iteration":867,"passed_time":10.40957114,"remaining_time":1.583022339},
{"learn":[0.1535689904],"iteration":868,"passed_time":10.42187168,"remaining_time":1.571076168},
{"learn":[0.1535440768],"iteration":869,"passed_time":10.4338187,"remaining_time":1.559076357},
{"learn":[0.1535202337],"iteration":870,"passed_time":10.44636884,"remaining_time":1.547165994},
{"learn":[0.1534923467],"iteration":871,"passed_time":10.45897487,"remaining_time":1.535262366},
{"learn":[0.1534818408],"iteration":872,"passed_time":10.47051453,"remaining_time":1.523202},
{"learn":[0.153475853],"iteration":873,"passed_time":10.48214493,"remaining_time":1.511155905},
{"learn":[0.1534544633],"iteration":874,"passed_time":10.49440027,"remaining_time":1.499200038},
{"learn":[0.1534406211],"iteration":875,"passed_time":10.50657134,"remaining_time":1.487231559},
{"learn":[0.1534156707],"iteration":876,"passed_time":10.51874283,"remaining_time":1.475262678},
{"learn":[0.1534040915],"iteration":877,"passed_time":10.53012711,"remaining_time":1.46318395},
{"learn":[0.1533828629],"iteration":878,"passed_time":10.54247965,"remaining_time":1.451240088},
{"learn":[0.1533680179],"iteration":879,"passed_time":10.5563544,"remaining_time":1.439502872},
{"learn":[0.1533580652],"iteration":880,"passed_time":10.56826543,"remaining_time":1.427495557},
{"learn":[0.1533353574],"iteration":881,"passed_time":10.58022445,"remaining_time":1.415494881},
{"learn":[0.1533177662],"iteration":882,"passed_time":10.59164314,"remaining_time":1.403422703},
{"learn":[0.1532924393],"iteration":883,"passed_time":10.60353837,"remaining_time":1.391414538},
{"learn":[0.1532772911],"iteration":884,"passed_time":10.61457347,"remaining_time":1.379294858},
{"learn":[0.1532469006],"iteration":885,"passed_time":10.62595101,"remaining_time":1.367221688},
{"learn":[0.1532319692],"iteration":886,"passed_time":10.63672163,"remaining_time":1.355072767},
{"learn":[0.1531954986],"iteration":887,"passed_time":10.64784807,"remaining_time":1.342971828},
{"learn":[0.1531799272],"iteration":888,"passed_time":10.65896847,"remaining_time":1.330872329},
{"learn":[0.1531521063],"iteration":889,"passed_time":10.67103568,"remaining_time":1.318892051},
{"learn":[0.1531322019],"iteration":890,"passed_time":10.68277712,"remaining_time":1.306871723},
{"learn":[0.1531036944],"iteration":891,"passed_time":10.6938946,"remaining_time":1.294776476},
{"learn":[0.1530947604],"iteration":892,"passed_time":10.70563541,"remaining_time":1.282758107},
{"learn":[0.1530853428],"iteration":893,"passed_time":10.717489,"remaining_time":1.270753729},
{"learn":[0.1530540563],"iteration":894,"passed_time":10.72949287,"remaining_time":1.25876732},
{"learn":[0.1530295863],"iteration":895,"passed_time":10.74171787,"remaining_time":1.246806538},
{"learn":[0.1530129176],"iteration":896,"passed_time":10.75458814,"remaining_time":1.234919262},
{"learn":[0.1529908018],"iteration":897,"passed_time":10.76656603,"remaining_time":1.222928435},
{"learn":[0.1529883446],"iteration":898,"passed_time":10.77755121,"remaining_time":1.210826109},
{"learn":[0.1529634391],"iteration":899,"passed_time":10.79015529,"remaining_time":1.198906143},
{"learn":[0.1529410812],"iteration":900,"passed_time":10.80300585,"remaining_time":1.187011742},
{"learn":[0.1529163387],"iteration":901,"passed_time":10.81547213,"remaining_time":1.175073468},
{"learn":[0.1528939825],"iteration":902,"passed_time":10.82901742,"remaining_time":1.163249933},
{"learn":[0.1528803601],"iteration":903,"passed_time":10.84161363,"remaining_time":1.151321801},
{"learn":[0.1528658696],"iteration":904,"passed_time":10.85478149,"remaining_time":1.139452201},
{"learn":[0.1528476986],"iteration":905,"passed_time":10.86734662,"remaining_time":1.127517199},
{"learn":[0.1528240049],"iteration":906,"passed_time":10.87930591,"remaining_time":1.115518688},
{"learn":[0.1528113505],"iteration":907,"passed_time":10.8918741,"remaining_time":1.103581957},
{"learn":[0.1527881095],"iteration":908,"passed_time":10.90404995,"remaining_time":1.09160456},
{"learn":[0.1527668596],"iteration":909,"passed_time":10.91655262,"remaining_time":1.07965905},
{"learn":[0.1527464795],"iteration":910,"passed_time":10.92842858,"remaining_time":1.067651091},
{"learn":[0.15272607],"iteration":911,"passed_time":10.94009327,"remaining_time":1.055623035},
{"learn":[0.1527145752],"iteration":912,"passed_time":10.95232648,"remaining_time":1.04364995},
{"learn":[0.1526992125],"iteration":913,"passed_time":10.9647867,"remaining_time":1.031697654},
{"learn":[0.1526807117],"iteration":914,"passed_time":10.97778559,"remaining_time":1.01979429},
{"learn":[0.1526584525],"iteration":915,"passed_time":10.99068391,"remaining_time":1.00787931},
{"learn":[0.1526441511],"iteration":916,"passed_time":11.00302886,"remaining_time":0.9959120993},
{"learn":[0.1526310933],"iteration":917,"passed_time":11.01564452,"remaining_time":0.983968247},
{"learn":[0.1526006554],"iteration":918,"passed_time":11.02782741,"remaining_time":0.9719847881},
{"learn":[0.1525853938],"iteration":919,"passed_time":11.04031954,"remaining_time":0.9600277864},
{"learn":[0.1525633807],"iteration":920,"passed_time":11.05201035,"remaining_time":0.9480008879},
{"learn":[0.1525526869],"iteration":921,"passed_time":11.06362402,"remaining_time":0.9359681922},
{"learn":[0.152527096],"iteration":922,"passed_time":11.07558704,"remaining_time":0.9239655491},
{"learn":[0.1525032495],"iteration":923,"passed_time":11.08810431,"remaining_time":0.9120085795},
{"learn":[0.1524763962],"iteration":924,"passed_time":11.10087005,"remaining_time":0.9000705444},
{"learn":[0.1524661664],"iteration":925,"passed_time":11.11259676,"remaining_time":0.8880476892},
{"learn":[0.1524561797],"iteration":926,"passed_time":11.12354148,"remaining_time":0.8759638923},
{"learn":[0.1524469477],"iteration":927,"passed_time":11.13394281,"remaining_time":0.8638403905},
{"learn":[0.1524290639],"iteration":928,"passed_time":11.14518131,"remaining_time":0.8517845779},
{"learn":[0.1524073981],"iteration":929,"passed_time":11.15601329,"remaining_time":0.8396999249},
{"learn":[0.1523920413],"iteration":930,"passed_time":11.16684678,"remaining_time":0.827618075},
{"learn":[0.1523767985],"iteration":931,"passed_time":11.1775213,"remaining_time":0.815527305},
{"learn":[0.1523536716],"iteration":932,"passed_time":11.18976891,"remaining_time":0.8035525372},
{"learn":[0.1523290637],"iteration":933,"passed_time":11.20210904,"remaining_time":0.7915837226},
{"learn":[0.1523151859],"iteration":934,"passed_time":11.21340518,"remaining_time":0.7795415363},
{"learn":[0.152287979],"iteration":935,"passed_time":11.22570815,"remaining_time":0.767569788},
{"learn":[0.1522696505],"iteration":936,"passed_time":11.23789183,"remaining_time":0.7555893122},
{"learn":[0.1522391225],"iteration":937,"passed_time":11.25065361,"remaining_time":0.7436466139},
{"learn":[0.1522282787],"iteration":938,"passed_time":11.26182179,"remaining_time":0.7315986468},
{"learn":[0.1522044355],"iteration":939,"passed_time":11.2739472,"remaining_time":0.7196136514},
{"learn":[0.1521925274],"iteration":940,"passed_time":11.28569429,"remaining_time":0.7076046365},
{"learn":[0.1521701426],"iteration":941,"passed_time":11.29729465,"remaining_time":0.6955871441},
{"learn":[0.152158623],"iteration":942,"passed_time":11.30894292,"remaining_time":0.6835734321},
{"learn":[0.1521329851],"iteration":943,"passed_time":11.32063452,"remaining_time":0.6715630648},
{"learn":[0.1521249325],"iteration":944,"passed_time":11.33267393,"remaining_time":0.6595736151},
{"learn":[0.1520950148],"iteration":945,"passed_time":11.3448094,"remaining_time":0.6475895428},
{"learn":[0.1520676032],"iteration":946,"passed_time":11.35718405,"remaining_time":0.6356185371},
{"learn":[0.1520472254],"iteration":947,"passed_time":11.36872224,"remaining_time":0.6236007982},
{"learn":[0.1520202211],"iteration":948,"passed_time":11.38083499,"remaining_time":0.6116149467},
{"learn":[0.1520054408],"iteration":949,"passed_time":11.39385741,"remaining_time":0.5996767058},
{"learn":[0.1519896144],"iteration":950,"passed_time":11.4076437,"remaining_time":0.587775543},
{"learn":[0.1519742466],"iteration":951,"passed_time":11.42039899,"remaining_time":0.5758184363},
{"learn":[0.1519531093],"iteration":952,"passed_time":11.43332833,"remaining_time":0.5638682386},
{"learn":[0.151932175],"iteration":953,"passed_time":11.44574708,"remaining_time":0.5518913689},
{"learn":[0.151912005],"iteration":954,"passed_time":11.45776471,"remaining_time":0.5398946721},
{"learn":[0.1519010996],"iteration":955,"passed_time":11.47012719,"remaining_time":0.5279138036},
{"learn":[0.1518882249],"iteration":956,"passed_time":11.48179143,"remaining_time":0.5159007643},
{"learn":[0.1518778201],"iteration":957,"passed_time":11.49363325,"remaining_time":0.5038962386},
{"learn":[0.151863129],"iteration":958,"passed_time":11.50557306,"remaining_time":0.4918962414},
{"learn":[0.1518532823],"iteration":959,"passed_time":11.51744066,"remaining_time":0.4798933606},
{"learn":[0.1518285807],"iteration":960,"passed_time":11.53009655,"remaining_time":0.4679227529},
{"learn":[0.1518081522],"iteration":961,"passed_time":11.54197644,"remaining_time":0.4559200674},
{"learn":[0.1517864826],"iteration":962,"passed_time":11.55341115,"remaining_time":0.4439005323},
{"learn":[0.1517717375],"iteration":963,"passed_time":11.56532503,"remaining_time":0.4319001047},
{"learn":[0.1517540435],"iteration":964,"passed_time":11.57710849,"remaining_time":0.4198951266},
{"learn":[0.1517162692],"iteration":965,"passed_time":11.58976253,"remaining_time":0.4079212485},
{"learn":[0.1516776982],"iteration":966,"passed_time":11.6020136,"remaining_time":0.3959322119},
{"learn":[0.1516529909],"iteration":967,"passed_time":11.61364833,"remaining_time":0.3839222589},
{"learn":[0.1516337483],"iteration":968,"passed_time":11.6243872,"remaining_time":0.3718844204},
{"learn":[0.1516078149],"iteration":969,"passed_time":11.63537484,"remaining_time":0.3598569539},
{"learn":[0.1515888126],"iteration":970,"passed_time":11.65520769,"remaining_time":0.3480958013},
{"learn":[0.1515562318],"iteration":971,"passed_time":11.66564739,"remaining_time":0.3360474557},
{"learn":[0.1515391266],"iteration":972,"passed_time":11.67698959,"remaining_time":0.3240274605},
{"learn":[0.151524239],"iteration":973,"passed_time":11.68739698,"remaining_time":0.311983903},
{"learn":[0.1514920031],"iteration":974,"passed_time":11.6981187,"remaining_time":0.2999517614},
{"learn":[0.1514690187],"iteration":975,"passed_time":11.70877292,"remaining_time":0.2879206455},
{"learn":[0.1514518476],"iteration":976,"passed_time":11.7204759,"remaining_time":0.2759170375},
{"learn":[0.1514272475],"iteration":977,"passed_time":11.73289394,"remaining_time":0.2639301295},
{"learn":[0.1514031441],"iteration":978,"passed_time":11.74513781,"remaining_time":0.2519386046},
{"learn":[0.1513809243],"iteration":979,"passed_time":11.75737672,"remaining_time":0.2399464636},
{"learn":[0.1513511986],"iteration":980,"passed_time":11.7703242,"remaining_time":0.2279675432},
{"learn":[0.1513438563],"iteration":981,"passed_time":11.78296243,"remaining_time":0.2159809814},
{"learn":[0.1513395849],"iteration":982,"passed_time":11.79509417,"remaining_time":0.2039843345},
{"learn":[0.1513209419],"iteration":983,"passed_time":11.80747916,"remaining_time":0.191991531},
{"learn":[0.1512973439],"iteration":984,"passed_time":11.81992164,"remaining_time":0.1799988067},
{"learn":[0.1512855511],"iteration":985,"passed_time":11.831494,"remaining_time":0.1679928154},
{"learn":[0.151265591],"iteration":986,"passed_time":11.84429856,"remaining_time":0.1560039324},
{"learn":[0.1512346434],"iteration":987,"passed_time":11.85779741,"remaining_time":0.1440218308},
{"learn":[0.1512150841],"iteration":988,"passed_time":11.869755,"remaining_time":0.1320195197},
{"learn":[0.1511868122],"iteration":989,"passed_time":11.88177211,"remaining_time":0.1200179001},
{"learn":[0.1511780201],"iteration":990,"passed_time":11.89338237,"remaining_time":0.1080125543},
{"learn":[0.151144991],"iteration":991,"passed_time":11.90526552,"remaining_time":0.09601020583},
{"learn":[0.1511209122],"iteration":992,"passed_time":11.91706461,"remaining_time":0.08400750482},
{"learn":[0.1511024514],"iteration":993,"passed_time":11.92902467,"remaining_time":0.07200618516},
{"learn":[0.1510780835],"iteration":994,"passed_time":11.94113789,"remaining_time":0.06000571803},
{"learn":[0.1510571314],"iteration":995,"passed_time":11.95297335,"remaining_time":0.04800390905},
{"learn":[0.1510402446],"iteration":996,"passed_time":11.96513064,"remaining_time":0.03600340213},
{"learn":[0.1510195088],"iteration":997,"passed_time":11.97770324,"remaining_time":0.0240034133},
{"learn":[0.1509986395],"iteration":998,"passed_time":11.98977948,"remaining_time":0.01200178126},
{"learn":[0.1509762008],"iteration":999,"passed_time":12.00258494,"remaining_time":0}
]}